[ {
  "rank" : 1,
  "name" : "ロードカナロア",
  "birthYear" : 2008,
  "color" : "鹿毛",
  "origin" : "新ひだか町",
  "runners" : 118,
  "winners" : 16,
  "starts" : 138,
  "wins" : 16,
  "prize" : 353893000,
  "prizePerStart" : 2564442,
  "prizePerHorse" : 2999093,
  "winRate" : 0.136,
  "earningIndex" : 1.67
}, {
  "rank" : 2,
  "name" : "エピファネイア",
  "birthYear" : 2010,
  "color" : "鹿毛",
  "origin" : "安平町",
  "runners" : 115,
  "winners" : 17,
  "starts" : 131,
  "wins" : 17,
  "prize" : 320428000,
  "prizePerStart" : 2446015,
  "prizePerHorse" : 2786330,
  "winRate" : 0.148,
  "earningIndex" : 1.55
}, {
  "rank" : 3,
  "name" : "キズナ",
  "birthYear" : 2010,
  "color" : "青鹿毛",
  "origin" : "新冠町",
  "runners" : 114,
  "winners" : 13,
  "starts" : 132,
  "wins" : 13,
  "prize" : 304037000,
  "prizePerStart" : 2303311,
  "prizePerHorse" : 2666991,
  "winRate" : 0.114,
  "earningIndex" : 1.49
}, {
  "rank" : 4,
  "name" : "レイデオロ",
  "birthYear" : 2014,
  "color" : "鹿毛",
  "origin" : "安平町",
  "runners" : 75,
  "winners" : 13,
  "starts" : 96,
  "wins" : 13,
  "prize" : 281213000,
  "prizePerStart" : 2929302,
  "prizePerHorse" : 3749507,
  "winRate" : 0.173,
  "earningIndex" : 2.09
}, {
  "rank" : 5,
  "name" : "キタサンブラック",
  "birthYear" : 2012,
  "color" : "鹿毛",
  "origin" : "日高町",
  "runners" : 89,
  "winners" : 13,
  "starts" : 102,
  "wins" : 13,
  "prize" : 271894000,
  "prizePerStart" : 2665627,
  "prizePerHorse" : 3054989,
  "winRate" : 0.146,
  "earningIndex" : 1.70
}, {
  "rank" : 6,
  "name" : "ドレフォン",
  "birthYear" : 2013,
  "color" : "鹿毛",
  "origin" : "米",
  "runners" : 112,
  "winners" : 13,
  "starts" : 145,
  "wins" : 13,
  "prize" : 227086000,
  "prizePerStart" : 1566110,
  "prizePerHorse" : 2027554,
  "winRate" : 0.116,
  "earningIndex" : 1.13
}, {
  "rank" : 7,
  "name" : "モーリス",
  "birthYear" : 2011,
  "color" : "鹿毛",
  "origin" : "日高町",
  "runners" : 88,
  "winners" : 10,
  "starts" : 104,
  "wins" : 11,
  "prize" : 215355000,
  "prizePerStart" : 2070721,
  "prizePerHorse" : 2447216,
  "winRate" : 0.114,
  "earningIndex" : 1.36
}, {
  "rank" : 8,
  "name" : "リオンディーズ",
  "birthYear" : 2013,
  "color" : "黒鹿毛",
  "origin" : "安平町",
  "runners" : 79,
  "winners" : 9,
  "starts" : 94,
  "wins" : 9,
  "prize" : 213225000,
  "prizePerStart" : 2268351,
  "prizePerHorse" : 2699051,
  "winRate" : 0.114,
  "earningIndex" : 1.51
}, {
  "rank" : 9,
  "name" : "シルバーステート",
  "birthYear" : 2013,
  "color" : "青鹿毛",
  "origin" : "安平町",
  "runners" : 106,
  "winners" : 12,
  "starts" : 128,
  "wins" : 12,
  "prize" : 206544000,
  "prizePerStart" : 1613625,
  "prizePerHorse" : 1948528,
  "winRate" : 0.113,
  "earningIndex" : 1.09
}, {
  "rank" : 10,
  "name" : "ドゥラメンテ",
  "birthYear" : 2012,
  "color" : "鹿毛",
  "origin" : "安平町",
  "runners" : 49,
  "winners" : 5,
  "starts" : 62,
  "wins" : 5,
  "prize" : 195812000,
  "prizePerStart" : 3158258,
  "prizePerHorse" : 3996163,
  "winRate" : 0.102,
  "earningIndex" : 2.23
}, {
  "rank" : 11,
  "name" : "サートゥルナーリア",
  "birthYear" : 2016,
  "color" : "黒鹿毛",
  "origin" : "安平町",
  "runners" : 77,
  "winners" : 7,
  "starts" : 90,
  "wins" : 7,
  "prize" : 179719000,
  "prizePerStart" : 1996878,
  "prizePerHorse" : 2334013,
  "winRate" : 0.091,
  "earningIndex" : 1.30
}, {
  "rank" : 12,
  "name" : "リアルスティール",
  "birthYear" : 2012,
  "color" : "鹿毛",
  "origin" : "安平町",
  "runners" : 81,
  "winners" : 3,
  "starts" : 94,
  "wins" : 3,
  "prize" : 160447000,
  "prizePerStart" : 1706883,
  "prizePerHorse" : 1980827,
  "winRate" : 0.037,
  "earningIndex" : 1.10
}, {
  "rank" : 13,
  "name" : "ルヴァンスレーヴ",
  "birthYear" : 2015,
  "color" : "鹿毛",
  "origin" : "白老町",
  "runners" : 70,
  "winners" : 11,
  "starts" : 91,
  "wins" : 11,
  "prize" : 155089000,
  "prizePerStart" : 1704275,
  "prizePerHorse" : 2215557,
  "winRate" : 0.157,
  "earningIndex" : 1.24
}, {
  "rank" : 14,
  "name" : "ブリックスアンドモルタル",
  "birthYear" : 2014,
  "color" : "黒鹿毛",
  "origin" : "米",
  "runners" : 72,
  "winners" : 7,
  "starts" : 85,
  "wins" : 7,
  "prize" : 146608000,
  "prizePerStart" : 1724800,
  "prizePerHorse" : 2036222,
  "winRate" : 0.097,
  "earningIndex" : 1.14
}, {
  "rank" : 15,
  "name" : "イスラボニータ",
  "birthYear" : 2011,
  "color" : "黒鹿毛",
  "origin" : "浦河町",
  "runners" : 55,
  "winners" : 4,
  "starts" : 64,
  "wins" : 4,
  "prize" : 132947000,
  "prizePerStart" : 2077297,
  "prizePerHorse" : 2417218,
  "winRate" : 0.073,
  "earningIndex" : 1.35
}, {
  "rank" : 16,
  "name" : "ナダル",
  "birthYear" : 2017,
  "color" : "鹿毛",
  "origin" : "米",
  "runners" : 50,
  "winners" : 8,
  "starts" : 62,
  "wins" : 8,
  "prize" : 126500000,
  "prizePerStart" : 2040323,
  "prizePerHorse" : 2530000,
  "winRate" : 0.160,
  "earningIndex" : 1.41
}, {
  "rank" : 17,
  "name" : "マインドユアビスケッツ",
  "birthYear" : 2013,
  "color" : "栗毛",
  "origin" : "米",
  "runners" : 53,
  "winners" : 7,
  "starts" : 67,
  "wins" : 7,
  "prize" : 125040000,
  "prizePerStart" : 1866269,
  "prizePerHorse" : 2359245,
  "winRate" : 0.132,
  "earningIndex" : 1.32
}, {
  "rank" : 18,
  "name" : "モズアスコット",
  "birthYear" : 2014,
  "color" : "栗毛",
  "origin" : "米",
  "runners" : 63,
  "winners" : 10,
  "starts" : 81,
  "wins" : 10,
  "prize" : 120574000,
  "prizePerStart" : 1488568,
  "prizePerHorse" : 1913873,
  "winRate" : 0.159,
  "earningIndex" : 1.07
}, {
  "rank" : 19,
  "name" : "サトノダイヤモンド",
  "birthYear" : 2013,
  "color" : "鹿毛",
  "origin" : "安平町",
  "runners" : 78,
  "winners" : 6,
  "starts" : 96,
  "wins" : 6,
  "prize" : 111955000,
  "prizePerStart" : 1166198,
  "prizePerHorse" : 1435321,
  "winRate" : 0.077,
  "earningIndex" : 0.80
}, {
  "rank" : 20,
  "name" : "ファインニードル",
  "birthYear" : 2013,
  "color" : "鹿毛",
  "origin" : "日高町",
  "runners" : 26,
  "winners" : 3,
  "starts" : 32,
  "wins" : 3,
  "prize" : 110608000,
  "prizePerStart" : 3456500,
  "prizePerHorse" : 4254154,
  "winRate" : 0.115,
  "earningIndex" : 2.37
}, {
  "rank" : 21,
  "name" : "シニスターミニスター",
  "birthYear" : 2003,
  "color" : "鹿毛",
  "origin" : "米",
  "runners" : 46,
  "winners" : 4,
  "starts" : 60,
  "wins" : 4,
  "prize" : 105886000,
  "prizePerStart" : 1764767,
  "prizePerHorse" : 2301870,
  "winRate" : 0.087,
  "earningIndex" : 1.28
}, {
  "rank" : 22,
  "name" : "オルフェーヴル",
  "birthYear" : 2008,
  "color" : "栗毛",
  "origin" : "白老町",
  "runners" : 67,
  "winners" : 6,
  "starts" : 84,
  "wins" : 6,
  "prize" : 104243000,
  "prizePerStart" : 1240988,
  "prizePerHorse" : 1555866,
  "winRate" : 0.090,
  "earningIndex" : 0.87
}, {
  "rank" : 23,
  "name" : "スクリーンヒーロー",
  "birthYear" : 2004,
  "color" : "栗毛",
  "origin" : "千歳市",
  "runners" : 21,
  "winners" : 4,
  "starts" : 26,
  "wins" : 4,
  "prize" : 97634000,
  "prizePerStart" : 3755154,
  "prizePerHorse" : 4649238,
  "winRate" : 0.190,
  "earningIndex" : 2.59
}, {
  "rank" : 24,
  "name" : "ルーラーシップ",
  "birthYear" : 2007,
  "color" : "鹿毛",
  "origin" : "安平町",
  "runners" : 55,
  "winners" : 3,
  "starts" : 68,
  "wins" : 3,
  "prize" : 90033000,
  "prizePerStart" : 1324015,
  "prizePerHorse" : 1636964,
  "winRate" : 0.055,
  "earningIndex" : 0.91
}, {
  "rank" : 25,
  "name" : "ニューイヤーズデイ",
  "birthYear" : 2011,
  "color" : "鹿毛",
  "origin" : "米",
  "runners" : 48,
  "winners" : 5,
  "starts" : 58,
  "wins" : 5,
  "prize" : 86996000,
  "prizePerStart" : 1499931,
  "prizePerHorse" : 1812417,
  "winRate" : 0.104,
  "earningIndex" : 1.01
}, {
  "rank" : 26,
  "name" : "スワーヴリチャード",
  "birthYear" : 2014,
  "color" : "栗毛",
  "origin" : "安平町",
  "runners" : 43,
  "winners" : 2,
  "starts" : 51,
  "wins" : 2,
  "prize" : 85851000,
  "prizePerStart" : 1683353,
  "prizePerHorse" : 1996535,
  "winRate" : 0.047,
  "earningIndex" : 1.11
}, {
  "rank" : 27,
  "name" : "カリフォルニアクローム",
  "birthYear" : 2011,
  "color" : "栗毛",
  "origin" : "米",
  "runners" : 38,
  "winners" : 5,
  "starts" : 47,
  "wins" : 6,
  "prize" : 81783000,
  "prizePerStart" : 1740064,
  "prizePerHorse" : 2152184,
  "winRate" : 0.132,
  "earningIndex" : 1.20
}, {
  "rank" : 28,
  "name" : "パイロ",
  "birthYear" : 2005,
  "color" : "黒鹿毛",
  "origin" : "米",
  "runners" : 37,
  "winners" : 5,
  "starts" : 49,
  "wins" : 5,
  "prize" : 77894000,
  "prizePerStart" : 1589673,
  "prizePerHorse" : 2105243,
  "winRate" : 0.135,
  "earningIndex" : 1.17
}, {
  "rank" : 29,
  "name" : "ハーツクライ",
  "birthYear" : 2001,
  "color" : "鹿毛",
  "origin" : "千歳市",
  "runners" : 31,
  "winners" : 2,
  "starts" : 35,
  "wins" : 2,
  "prize" : 77077000,
  "prizePerStart" : 2202200,
  "prizePerHorse" : 2486355,
  "winRate" : 0.065,
  "earningIndex" : 1.39
}, {
  "rank" : 30,
  "name" : "ヘニーヒューズ",
  "birthYear" : 2003,
  "color" : "栗毛",
  "origin" : "米",
  "runners" : 35,
  "winners" : 2,
  "starts" : 44,
  "wins" : 2,
  "prize" : 75318000,
  "prizePerStart" : 1711773,
  "prizePerHorse" : 2151943,
  "winRate" : 0.057,
  "earningIndex" : 1.20
}, {
  "rank" : 31,
  "name" : "ハービンジャー",
  "birthYear" : 2006,
  "color" : "鹿毛",
  "origin" : "英",
  "runners" : 42,
  "winners" : 2,
  "starts" : 52,
  "wins" : 2,
  "prize" : 68851000,
  "prizePerStart" : 1324058,
  "prizePerHorse" : 1639310,
  "winRate" : 0.048,
  "earningIndex" : 0.91
}, {
  "rank" : 32,
  "name" : "ミッキーアイル",
  "birthYear" : 2011,
  "color" : "鹿毛",
  "origin" : "安平町",
  "runners" : 51,
  "winners" : 3,
  "starts" : 63,
  "wins" : 3,
  "prize" : 62787000,
  "prizePerStart" : 996619,
  "prizePerHorse" : 1231118,
  "winRate" : 0.059,
  "earningIndex" : 0.69
}, {
  "rank" : 33,
  "name" : "サンダースノー",
  "birthYear" : 2014,
  "color" : "鹿毛",
  "origin" : "愛",
  "runners" : 40,
  "winners" : 5,
  "starts" : 44,
  "wins" : 5,
  "prize" : 59918000,
  "prizePerStart" : 1361773,
  "prizePerHorse" : 1497950,
  "winRate" : 0.125,
  "earningIndex" : 0.84
}, {
  "rank" : 34,
  "name" : "コントレイル",
  "birthYear" : 2017,
  "color" : "青鹿毛",
  "origin" : "新冠町",
  "runners" : 56,
  "winners" : 4,
  "starts" : 69,
  "wins" : 4,
  "prize" : 58590000,
  "prizePerStart" : 849130,
  "prizePerHorse" : 1046250,
  "winRate" : 0.071,
  "earningIndex" : 0.58
}, {
  "rank" : 35,
  "name" : "ディスクリートキャット",
  "birthYear" : 2003,
  "color" : "鹿毛",
  "origin" : "米",
  "runners" : 35,
  "winners" : 2,
  "starts" : 42,
  "wins" : 2,
  "prize" : 58310000,
  "prizePerStart" : 1388333,
  "prizePerHorse" : 1666000,
  "winRate" : 0.057,
  "earningIndex" : 0.93
}, {
  "rank" : 36,
  "name" : "ゴールドシップ",
  "birthYear" : 2009,
  "color" : "芦毛",
  "origin" : "日高町",
  "runners" : 61,
  "winners" : 0,
  "starts" : 80,
  "wins" : 0,
  "prize" : 55598000,
  "prizePerStart" : 694975,
  "prizePerHorse" : 911443,
  "winRate" : 0.000,
  "earningIndex" : 0.51
}, {
  "rank" : 37,
  "name" : "Frosted",
  "birthYear" : 2012,
  "color" : "",
  "origin" : "米",
  "runners" : 5,
  "winners" : 3,
  "starts" : 5,
  "wins" : 3,
  "prize" : 54292000,
  "prizePerStart" : 10858400,
  "prizePerHorse" : 10858400,
  "winRate" : 0.600,
  "earningIndex" : 6.06
}, {
  "rank" : 38,
  "name" : "アニマルキングダム",
  "birthYear" : 2008,
  "color" : "栗毛",
  "origin" : "米",
  "runners" : 11,
  "winners" : 3,
  "starts" : 13,
  "wins" : 3,
  "prize" : 53292000,
  "prizePerStart" : 4099385,
  "prizePerHorse" : 4844727,
  "winRate" : 0.273,
  "earningIndex" : 2.70
}, {
  "rank" : 39,
  "name" : "シスキン",
  "birthYear" : 2017,
  "color" : "鹿毛",
  "origin" : "米",
  "runners" : 24,
  "winners" : 4,
  "starts" : 27,
  "wins" : 4,
  "prize" : 52382000,
  "prizePerStart" : 1940074,
  "prizePerHorse" : 2182583,
  "winRate" : 0.167,
  "earningIndex" : 1.22
}, {
  "rank" : 40,
  "name" : "ダノンバラード",
  "birthYear" : 2008,
  "color" : "黒鹿毛",
  "origin" : "新ひだか町",
  "runners" : 38,
  "winners" : 1,
  "starts" : 51,
  "wins" : 1,
  "prize" : 52016000,
  "prizePerStart" : 1019922,
  "prizePerHorse" : 1368842,
  "winRate" : 0.026,
  "earningIndex" : 0.76
}, {
  "rank" : 41,
  "name" : "アメリカンペイトリオット",
  "birthYear" : 2013,
  "color" : "鹿毛",
  "origin" : "米",
  "runners" : 41,
  "winners" : 2,
  "starts" : 48,
  "wins" : 2,
  "prize" : 51430000,
  "prizePerStart" : 1071458,
  "prizePerHorse" : 1254390,
  "winRate" : 0.049,
  "earningIndex" : 0.70
}, {
  "rank" : 42,
  "name" : "デクラレーションオブウォー",
  "birthYear" : 2009,
  "color" : "鹿毛",
  "origin" : "米",
  "runners" : 37,
  "winners" : 3,
  "starts" : 46,
  "wins" : 3,
  "prize" : 50990000,
  "prizePerStart" : 1108478,
  "prizePerHorse" : 1378108,
  "winRate" : 0.081,
  "earningIndex" : 0.77
}, {
  "rank" : 43,
  "name" : "タリスマニック",
  "birthYear" : 2013,
  "color" : "黒鹿毛",
  "origin" : "英",
  "runners" : 23,
  "winners" : 2,
  "starts" : 29,
  "wins" : 2,
  "prize" : 49618000,
  "prizePerStart" : 1710966,
  "prizePerHorse" : 2157304,
  "winRate" : 0.087,
  "earningIndex" : 1.20
}, {
  "rank" : 44,
  "name" : "ポエティックフレア",
  "birthYear" : 2018,
  "color" : "鹿毛",
  "origin" : "愛",
  "runners" : 20,
  "winners" : 5,
  "starts" : 25,
  "wins" : 5,
  "prize" : 49578000,
  "prizePerStart" : 1983120,
  "prizePerHorse" : 2478900,
  "winRate" : 0.250,
  "earningIndex" : 1.38
}, {
  "rank" : 45,
  "name" : "サトノアラジン",
  "birthYear" : 2011,
  "color" : "鹿毛",
  "origin" : "安平町",
  "runners" : 37,
  "winners" : 4,
  "starts" : 48,
  "wins" : 4,
  "prize" : 49150000,
  "prizePerStart" : 1023958,
  "prizePerHorse" : 1328378,
  "winRate" : 0.108,
  "earningIndex" : 0.74
}, {
  "rank" : 46,
  "name" : "サトノクラウン",
  "birthYear" : 2012,
  "color" : "黒鹿毛",
  "origin" : "安平町",
  "runners" : 32,
  "winners" : 3,
  "starts" : 37,
  "wins" : 3,
  "prize" : 48358000,
  "prizePerStart" : 1306973,
  "prizePerHorse" : 1511188,
  "winRate" : 0.094,
  "earningIndex" : 0.84
}, {
  "rank" : 47,
  "name" : "ホッコータルマエ",
  "birthYear" : 2009,
  "color" : "鹿毛",
  "origin" : "浦河町",
  "runners" : 44,
  "winners" : 1,
  "starts" : 56,
  "wins" : 1,
  "prize" : 47580000,
  "prizePerStart" : 849643,
  "prizePerHorse" : 1081364,
  "winRate" : 0.023,
  "earningIndex" : 0.60
}, {
  "rank" : 48,
  "name" : "クリソベリル",
  "birthYear" : 2016,
  "color" : "鹿毛",
  "origin" : "安平町",
  "runners" : 46,
  "winners" : 3,
  "starts" : 64,
  "wins" : 3,
  "prize" : 47520000,
  "prizePerStart" : 742500,
  "prizePerHorse" : 1033043,
  "winRate" : 0.065,
  "earningIndex" : 0.58
}, {
  "rank" : 49,
  "name" : "ジャスタウェイ",
  "birthYear" : 2009,
  "color" : "鹿毛",
  "origin" : "浦河町",
  "runners" : 36,
  "winners" : 2,
  "starts" : 44,
  "wins" : 2,
  "prize" : 44938000,
  "prizePerStart" : 1021318,
  "prizePerHorse" : 1248278,
  "winRate" : 0.056,
  "earningIndex" : 0.70
}, {
  "rank" : 50,
  "name" : "タワーオブロンドン",
  "birthYear" : 2015,
  "color" : "鹿毛",
  "origin" : "日高町",
  "runners" : 36,
  "winners" : 2,
  "starts" : 42,
  "wins" : 2,
  "prize" : 44184000,
  "prizePerStart" : 1052000,
  "prizePerHorse" : 1227333,
  "winRate" : 0.056,
  "earningIndex" : 0.68
}, {
  "rank" : 51,
  "name" : "ジョーカプチーノ",
  "birthYear" : 2006,
  "color" : "芦毛",
  "origin" : "浦河町",
  "runners" : 11,
  "winners" : 1,
  "starts" : 13,
  "wins" : 1,
  "prize" : 44039000,
  "prizePerStart" : 3387615,
  "prizePerHorse" : 4003545,
  "winRate" : 0.091,
  "earningIndex" : 2.23
}, {
  "rank" : 52,
  "name" : "ディープインパクト",
  "birthYear" : 2002,
  "color" : "鹿毛",
  "origin" : "早来町",
  "runners" : 13,
  "winners" : 2,
  "starts" : 13,
  "wins" : 2,
  "prize" : 43123000,
  "prizePerStart" : 3317154,
  "prizePerHorse" : 3317154,
  "winRate" : 0.154,
  "earningIndex" : 1.85
}, {
  "rank" : 53,
  "name" : "ビッグアーサー",
  "birthYear" : 2011,
  "color" : "鹿毛",
  "origin" : "浦河町",
  "runners" : 45,
  "winners" : 2,
  "starts" : 51,
  "wins" : 2,
  "prize" : 41138000,
  "prizePerStart" : 806627,
  "prizePerHorse" : 914178,
  "winRate" : 0.044,
  "earningIndex" : 0.51
}, {
  "rank" : 54,
  "name" : "ゴールドドリーム",
  "birthYear" : 2013,
  "color" : "鹿毛",
  "origin" : "安平町",
  "runners" : 37,
  "winners" : 2,
  "starts" : 51,
  "wins" : 2,
  "prize" : 40110000,
  "prizePerStart" : 786471,
  "prizePerHorse" : 1084054,
  "winRate" : 0.054,
  "earningIndex" : 0.60
}, {
  "rank" : 55,
  "name" : "アドマイヤマーズ",
  "birthYear" : 2016,
  "color" : "栗毛",
  "origin" : "安平町",
  "runners" : 35,
  "winners" : 2,
  "starts" : 41,
  "wins" : 2,
  "prize" : 39870000,
  "prizePerStart" : 972439,
  "prizePerHorse" : 1139143,
  "winRate" : 0.057,
  "earningIndex" : 0.64
}, {
  "rank" : 56,
  "name" : "マクフィ",
  "birthYear" : 2007,
  "color" : "鹿毛",
  "origin" : "英",
  "runners" : 29,
  "winners" : 2,
  "starts" : 34,
  "wins" : 2,
  "prize" : 38826000,
  "prizePerStart" : 1141941,
  "prizePerHorse" : 1338828,
  "winRate" : 0.069,
  "earningIndex" : 0.75
}, {
  "rank" : 57,
  "name" : "Frankel",
  "birthYear" : 2008,
  "color" : "",
  "origin" : "英",
  "runners" : 14,
  "winners" : 2,
  "starts" : 14,
  "wins" : 2,
  "prize" : 38821000,
  "prizePerStart" : 2772929,
  "prizePerHorse" : 2772929,
  "winRate" : 0.143,
  "earningIndex" : 1.55
}, {
  "rank" : 58,
  "name" : "ミスターメロディ",
  "birthYear" : 2015,
  "color" : "鹿毛",
  "origin" : "米",
  "runners" : 32,
  "winners" : 4,
  "starts" : 39,
  "wins" : 4,
  "prize" : 38776000,
  "prizePerStart" : 994256,
  "prizePerHorse" : 1211750,
  "winRate" : 0.125,
  "earningIndex" : 0.68
}, {
  "rank" : 59,
  "name" : "Into Mischief",
  "birthYear" : 2005,
  "color" : "",
  "origin" : "米",
  "runners" : 9,
  "winners" : 1,
  "starts" : 11,
  "wins" : 1,
  "prize" : 38188000,
  "prizePerStart" : 3471636,
  "prizePerHorse" : 4243111,
  "winRate" : 0.111,
  "earningIndex" : 2.37
}, {
  "rank" : 60,
  "name" : "ロジャーバローズ",
  "birthYear" : 2016,
  "color" : "鹿毛",
  "origin" : "新ひだか町",
  "runners" : 22,
  "winners" : 2,
  "starts" : 35,
  "wins" : 2,
  "prize" : 36841000,
  "prizePerStart" : 1052600,
  "prizePerHorse" : 1674591,
  "winRate" : 0.091,
  "earningIndex" : 0.93
}, {
  "rank" : 61,
  "name" : "リアルインパクト",
  "birthYear" : 2008,
  "color" : "鹿毛",
  "origin" : "安平町",
  "runners" : 14,
  "winners" : 2,
  "starts" : 16,
  "wins" : 2,
  "prize" : 36776000,
  "prizePerStart" : 2298500,
  "prizePerHorse" : 2626857,
  "winRate" : 0.143,
  "earningIndex" : 1.47
}, {
  "rank" : 62,
  "name" : "ダイワメジャー",
  "birthYear" : 2001,
  "color" : "栗毛",
  "origin" : "千歳市",
  "runners" : 32,
  "winners" : 0,
  "starts" : 35,
  "wins" : 0,
  "prize" : 36602000,
  "prizePerStart" : 1045771,
  "prizePerHorse" : 1143813,
  "winRate" : 0.000,
  "earningIndex" : 0.64
}, {
  "rank" : 63,
  "name" : "インディチャンプ",
  "birthYear" : 2015,
  "color" : "鹿毛",
  "origin" : "安平町",
  "runners" : 26,
  "winners" : 3,
  "starts" : 30,
  "wins" : 3,
  "prize" : 36166000,
  "prizePerStart" : 1205533,
  "prizePerHorse" : 1391000,
  "winRate" : 0.115,
  "earningIndex" : 0.78
}, {
  "rank" : 64,
  "name" : "ダノンレジェンド",
  "birthYear" : 2010,
  "color" : "黒鹿毛",
  "origin" : "米",
  "runners" : 23,
  "winners" : 2,
  "starts" : 27,
  "wins" : 2,
  "prize" : 35750000,
  "prizePerStart" : 1324074,
  "prizePerHorse" : 1554348,
  "winRate" : 0.087,
  "earningIndex" : 0.87
}, {
  "rank" : 65,
  "name" : "アルアイン",
  "birthYear" : 2014,
  "color" : "鹿毛",
  "origin" : "安平町",
  "runners" : 35,
  "winners" : 0,
  "starts" : 42,
  "wins" : 0,
  "prize" : 34600000,
  "prizePerStart" : 823810,
  "prizePerHorse" : 988571,
  "winRate" : 0.000,
  "earningIndex" : 0.55
}, {
  "rank" : 66,
  "name" : "フィエールマン",
  "birthYear" : 2015,
  "color" : "鹿毛",
  "origin" : "安平町",
  "runners" : 34,
  "winners" : 0,
  "starts" : 42,
  "wins" : 0,
  "prize" : 34247000,
  "prizePerStart" : 815405,
  "prizePerHorse" : 1007265,
  "winRate" : 0.000,
  "earningIndex" : 0.56
}, {
  "rank" : 67,
  "name" : "ダンカーク",
  "birthYear" : 2006,
  "color" : "芦毛",
  "origin" : "米",
  "runners" : 9,
  "winners" : 1,
  "starts" : 10,
  "wins" : 1,
  "prize" : 34214000,
  "prizePerStart" : 3421400,
  "prizePerHorse" : 3801556,
  "winRate" : 0.111,
  "earningIndex" : 2.12
}, {
  "rank" : 68,
  "name" : "ブラックタイド",
  "birthYear" : 2001,
  "color" : "黒鹿毛",
  "origin" : "早来町",
  "runners" : 16,
  "winners" : 1,
  "starts" : 17,
  "wins" : 1,
  "prize" : 31587000,
  "prizePerStart" : 1858059,
  "prizePerHorse" : 1974188,
  "winRate" : 0.063,
  "earningIndex" : 1.10
}, {
  "rank" : 69,
  "name" : "Saxon Warrior",
  "birthYear" : 2015,
  "color" : "",
  "origin" : "日",
  "runners" : 5,
  "winners" : 2,
  "starts" : 6,
  "wins" : 2,
  "prize" : 31287000,
  "prizePerStart" : 5214500,
  "prizePerHorse" : 6257400,
  "winRate" : 0.400,
  "earningIndex" : 3.49
}, {
  "rank" : 70,
  "name" : "シャンハイボビー",
  "birthYear" : 2010,
  "color" : "青鹿毛",
  "origin" : "米",
  "runners" : 32,
  "winners" : 1,
  "starts" : 39,
  "wins" : 1,
  "prize" : 28598000,
  "prizePerStart" : 733282,
  "prizePerHorse" : 893688,
  "winRate" : 0.031,
  "earningIndex" : 0.50
}, {
  "rank" : 71,
  "name" : "スズカコーズウェイ",
  "birthYear" : 2004,
  "color" : "栗毛",
  "origin" : "静内町",
  "runners" : 6,
  "winners" : 1,
  "starts" : 8,
  "wins" : 1,
  "prize" : 28220000,
  "prizePerStart" : 3527500,
  "prizePerHorse" : 4703333,
  "winRate" : 0.167,
  "earningIndex" : 2.62
}, {
  "rank" : 72,
  "name" : "フォーウィールドライブ",
  "birthYear" : 2017,
  "color" : "鹿毛",
  "origin" : "米",
  "runners" : 29,
  "winners" : 1,
  "starts" : 32,
  "wins" : 1,
  "prize" : 27801000,
  "prizePerStart" : 868781,
  "prizePerHorse" : 958655,
  "winRate" : 0.034,
  "earningIndex" : 0.53
}, {
  "rank" : 73,
  "name" : "ダノンプレミアム",
  "birthYear" : 2015,
  "color" : "青鹿毛",
  "origin" : "新ひだか町",
  "runners" : 36,
  "winners" : 0,
  "starts" : 51,
  "wins" : 0,
  "prize" : 27140000,
  "prizePerStart" : 532157,
  "prizePerHorse" : 753889,
  "winRate" : 0.000,
  "earningIndex" : 0.42
}, {
  "rank" : 74,
  "name" : "マジェスティックウォリアー",
  "birthYear" : 2005,
  "color" : "鹿毛",
  "origin" : "米",
  "runners" : 38,
  "winners" : 2,
  "starts" : 45,
  "wins" : 2,
  "prize" : 27050000,
  "prizePerStart" : 601111,
  "prizePerHorse" : 711842,
  "winRate" : 0.053,
  "earningIndex" : 0.40
}, {
  "rank" : 75,
  "name" : "グレーターロンドン",
  "birthYear" : 2012,
  "color" : "鹿毛",
  "origin" : "日高町",
  "runners" : 22,
  "winners" : 1,
  "starts" : 27,
  "wins" : 1,
  "prize" : 27000000,
  "prizePerStart" : 1000000,
  "prizePerHorse" : 1227273,
  "winRate" : 0.045,
  "earningIndex" : 0.68
}, {
  "rank" : 76,
  "name" : "ダノンスマッシュ",
  "birthYear" : 2015,
  "color" : "鹿毛",
  "origin" : "新ひだか町",
  "runners" : 34,
  "winners" : 1,
  "starts" : 39,
  "wins" : 1,
  "prize" : 24921000,
  "prizePerStart" : 639000,
  "prizePerHorse" : 732971,
  "winRate" : 0.029,
  "earningIndex" : 0.41
}, {
  "rank" : 77,
  "name" : "Gun Runner",
  "birthYear" : 2013,
  "color" : "",
  "origin" : "米",
  "runners" : 10,
  "winners" : 3,
  "starts" : 13,
  "wins" : 3,
  "prize" : 24656000,
  "prizePerStart" : 1896615,
  "prizePerHorse" : 2465600,
  "winRate" : 0.300,
  "earningIndex" : 1.38
}, {
  "rank" : 78,
  "name" : "ウインブライト",
  "birthYear" : 2014,
  "color" : "芦毛",
  "origin" : "新冠町",
  "runners" : 30,
  "winners" : 1,
  "starts" : 36,
  "wins" : 1,
  "prize" : 24228000,
  "prizePerStart" : 673000,
  "prizePerHorse" : 807600,
  "winRate" : 0.033,
  "earningIndex" : 0.45
}, {
  "rank" : 79,
  "name" : "エイシンヒカリ",
  "birthYear" : 2011,
  "color" : "芦毛",
  "origin" : "新ひだか町",
  "runners" : 15,
  "winners" : 1,
  "starts" : 21,
  "wins" : 1,
  "prize" : 23440000,
  "prizePerStart" : 1116190,
  "prizePerHorse" : 1562667,
  "winRate" : 0.067,
  "earningIndex" : 0.87
}, {
  "rank" : 80,
  "name" : "ハクサンムーン",
  "birthYear" : 2009,
  "color" : "栗毛",
  "origin" : "日高町",
  "runners" : 5,
  "winners" : 2,
  "starts" : 7,
  "wins" : 2,
  "prize" : 22905000,
  "prizePerStart" : 3272143,
  "prizePerHorse" : 4581000,
  "winRate" : 0.400,
  "earningIndex" : 2.56
}, {
  "rank" : 81,
  "name" : "ヤマカツエース",
  "birthYear" : 2012,
  "color" : "栗毛",
  "origin" : "新ひだか町",
  "runners" : 5,
  "winners" : 1,
  "starts" : 7,
  "wins" : 1,
  "prize" : 22296000,
  "prizePerStart" : 3185143,
  "prizePerHorse" : 4459200,
  "winRate" : 0.200,
  "earningIndex" : 2.49
}, {
  "rank" : 82,
  "name" : "ヘンリーバローズ",
  "birthYear" : 2015,
  "color" : "鹿毛",
  "origin" : "安平町",
  "runners" : 9,
  "winners" : 1,
  "starts" : 12,
  "wins" : 1,
  "prize" : 21978000,
  "prizePerStart" : 1831500,
  "prizePerHorse" : 2442000,
  "winRate" : 0.111,
  "earningIndex" : 1.36
}, {
  "rank" : 83,
  "name" : "コパノリッキー",
  "birthYear" : 2010,
  "color" : "栗毛",
  "origin" : "日高町",
  "runners" : 26,
  "winners" : 0,
  "starts" : 33,
  "wins" : 0,
  "prize" : 21653000,
  "prizePerStart" : 656152,
  "prizePerHorse" : 832808,
  "winRate" : 0.000,
  "earningIndex" : 0.46
}, {
  "rank" : 84,
  "name" : "エスポワールシチー",
  "birthYear" : 2005,
  "color" : "栗毛",
  "origin" : "門別町",
  "runners" : 16,
  "winners" : 1,
  "starts" : 21,
  "wins" : 1,
  "prize" : 21380000,
  "prizePerStart" : 1018095,
  "prizePerHorse" : 1336250,
  "winRate" : 0.063,
  "earningIndex" : 0.75
}, {
  "rank" : 85,
  "name" : "トーセンラー",
  "birthYear" : 2008,
  "color" : "黒鹿毛",
  "origin" : "千歳市",
  "runners" : 13,
  "winners" : 1,
  "starts" : 14,
  "wins" : 1,
  "prize" : 21240000,
  "prizePerStart" : 1517143,
  "prizePerHorse" : 1633846,
  "winRate" : 0.077,
  "earningIndex" : 0.91
}, {
  "rank" : 86,
  "name" : "ラブリーデイ",
  "birthYear" : 2010,
  "color" : "黒鹿毛",
  "origin" : "安平町",
  "runners" : 17,
  "winners" : 0,
  "starts" : 22,
  "wins" : 0,
  "prize" : 21210000,
  "prizePerStart" : 964091,
  "prizePerHorse" : 1247647,
  "winRate" : 0.000,
  "earningIndex" : 0.70
}, {
  "rank" : 87,
  "name" : "Collected",
  "birthYear" : 2013,
  "color" : "",
  "origin" : "",
  "runners" : 3,
  "winners" : 2,
  "starts" : 4,
  "wins" : 2,
  "prize" : 20644000,
  "prizePerStart" : 5161000,
  "prizePerHorse" : 6881333,
  "winRate" : 0.667,
  "earningIndex" : 3.84
}, {
  "rank" : 88,
  "name" : "ベンバトル",
  "birthYear" : 2014,
  "color" : "鹿毛",
  "origin" : "英",
  "runners" : 25,
  "winners" : 2,
  "starts" : 34,
  "wins" : 2,
  "prize" : 20630000,
  "prizePerStart" : 606765,
  "prizePerHorse" : 825200,
  "winRate" : 0.080,
  "earningIndex" : 0.46
}, {
  "rank" : 89,
  "name" : "ミッキーロケット",
  "birthYear" : 2013,
  "color" : "鹿毛",
  "origin" : "安平町",
  "runners" : 13,
  "winners" : 2,
  "starts" : 16,
  "wins" : 2,
  "prize" : 20570000,
  "prizePerStart" : 1285625,
  "prizePerHorse" : 1582308,
  "winRate" : 0.154,
  "earningIndex" : 0.88
}, {
  "rank" : 90,
  "name" : "ディーマジェスティ",
  "birthYear" : 2013,
  "color" : "鹿毛",
  "origin" : "新ひだか町",
  "runners" : 23,
  "winners" : 1,
  "starts" : 28,
  "wins" : 1,
  "prize" : 20510000,
  "prizePerStart" : 732500,
  "prizePerHorse" : 891739,
  "winRate" : 0.043,
  "earningIndex" : 0.50
}, {
  "rank" : 91,
  "name" : "Harry Angel",
  "birthYear" : 2014,
  "color" : "",
  "origin" : "",
  "runners" : 1,
  "winners" : 1,
  "starts" : 2,
  "wins" : 1,
  "prize" : 20194000,
  "prizePerStart" : 10097000,
  "prizePerHorse" : 20194000,
  "winRate" : 1.000,
  "earningIndex" : 11.26
}, {
  "rank" : 92,
  "name" : "フィレンツェファイア",
  "birthYear" : 2015,
  "color" : "鹿毛",
  "origin" : "米",
  "runners" : 15,
  "winners" : 2,
  "starts" : 18,
  "wins" : 2,
  "prize" : 19032000,
  "prizePerStart" : 1057333,
  "prizePerHorse" : 1268800,
  "winRate" : 0.133,
  "earningIndex" : 0.71
}, {
  "rank" : 93,
  "name" : "モーニン",
  "birthYear" : 2012,
  "color" : "栗毛",
  "origin" : "米",
  "runners" : 21,
  "winners" : 1,
  "starts" : 30,
  "wins" : 1,
  "prize" : 18680000,
  "prizePerStart" : 622667,
  "prizePerHorse" : 889524,
  "winRate" : 0.048,
  "earningIndex" : 0.50
}, {
  "rank" : 94,
  "name" : "ミスチヴィアスアレックス",
  "birthYear" : 2017,
  "color" : "鹿毛",
  "origin" : "米",
  "runners" : 26,
  "winners" : 2,
  "starts" : 29,
  "wins" : 2,
  "prize" : 17840000,
  "prizePerStart" : 615172,
  "prizePerHorse" : 686154,
  "winRate" : 0.077,
  "earningIndex" : 0.38
}, {
  "rank" : 95,
  "name" : "カレンブラックヒル",
  "birthYear" : 2009,
  "color" : "黒鹿毛",
  "origin" : "安平町",
  "runners" : 21,
  "winners" : 1,
  "starts" : 26,
  "wins" : 1,
  "prize" : 17494000,
  "prizePerStart" : 672846,
  "prizePerHorse" : 833048,
  "winRate" : 0.048,
  "earningIndex" : 0.46
}, {
  "rank" : 96,
  "name" : "Justify",
  "birthYear" : 2015,
  "color" : "",
  "origin" : "米",
  "runners" : 9,
  "winners" : 1,
  "starts" : 10,
  "wins" : 1,
  "prize" : 17188000,
  "prizePerStart" : 1718800,
  "prizePerHorse" : 1909778,
  "winRate" : 0.111,
  "earningIndex" : 1.07
}, {
  "rank" : 97,
  "name" : "ベストウォーリア",
  "birthYear" : 2010,
  "color" : "栗毛",
  "origin" : "米",
  "runners" : 13,
  "winners" : 1,
  "starts" : 15,
  "wins" : 1,
  "prize" : 17145000,
  "prizePerStart" : 1143000,
  "prizePerHorse" : 1318846,
  "winRate" : 0.077,
  "earningIndex" : 0.74
}, {
  "rank" : 98,
  "name" : "Charlatan",
  "birthYear" : 2017,
  "color" : "栗毛",
  "origin" : "米",
  "runners" : 3,
  "winners" : 1,
  "starts" : 5,
  "wins" : 1,
  "prize" : 16958000,
  "prizePerStart" : 3391600,
  "prizePerHorse" : 5652667,
  "winRate" : 0.333,
  "earningIndex" : 3.15
}, {
  "rank" : 99,
  "name" : "ミッキーグローリー",
  "birthYear" : 2013,
  "color" : "青鹿毛",
  "origin" : "新ひだか町",
  "runners" : 7,
  "winners" : 1,
  "starts" : 9,
  "wins" : 1,
  "prize" : 16800000,
  "prizePerStart" : 1866667,
  "prizePerHorse" : 2400000,
  "winRate" : 0.143,
  "earningIndex" : 1.34
}, {
  "rank" : 100,
  "name" : "バゴ",
  "birthYear" : 2001,
  "color" : "黒鹿毛",
  "origin" : "仏",
  "runners" : 18,
  "winners" : 1,
  "starts" : 24,
  "wins" : 1,
  "prize" : 16405000,
  "prizePerStart" : 683542,
  "prizePerHorse" : 911389,
  "winRate" : 0.056,
  "earningIndex" : 0.51
}, {
  "rank" : 101,
  "name" : "キングカメハメハ",
  "birthYear" : 2001,
  "color" : "鹿毛",
  "origin" : "早来町",
  "runners" : 11,
  "winners" : 0,
  "starts" : 12,
  "wins" : 0,
  "prize" : 16028000,
  "prizePerStart" : 1335667,
  "prizePerHorse" : 1457091,
  "winRate" : 0.000,
  "earningIndex" : 0.81
}, {
  "rank" : 102,
  "name" : "マテラスカイ",
  "birthYear" : 2014,
  "color" : "栗毛",
  "origin" : "米",
  "runners" : 19,
  "winners" : 2,
  "starts" : 24,
  "wins" : 2,
  "prize" : 15970000,
  "prizePerStart" : 665417,
  "prizePerHorse" : 840526,
  "winRate" : 0.105,
  "earningIndex" : 0.47
}, {
  "rank" : 103,
  "name" : "Speightstown",
  "birthYear" : 1998,
  "color" : "",
  "origin" : "米",
  "runners" : 5,
  "winners" : 1,
  "starts" : 5,
  "wins" : 1,
  "prize" : 15898000,
  "prizePerStart" : 3179600,
  "prizePerHorse" : 3179600,
  "winRate" : 0.200,
  "earningIndex" : 1.77
}, {
  "rank" : 104,
  "name" : "Kingman",
  "birthYear" : 2011,
  "color" : "",
  "origin" : "英",
  "runners" : 7,
  "winners" : 1,
  "starts" : 9,
  "wins" : 1,
  "prize" : 15476000,
  "prizePerStart" : 1719556,
  "prizePerHorse" : 2210857,
  "winRate" : 0.143,
  "earningIndex" : 1.23
}, {
  "rank" : 105,
  "name" : "アジアエクスプレス",
  "birthYear" : 2011,
  "color" : "栗毛",
  "origin" : "米",
  "runners" : 28,
  "winners" : 1,
  "starts" : 40,
  "wins" : 1,
  "prize" : 15300000,
  "prizePerStart" : 382500,
  "prizePerHorse" : 546429,
  "winRate" : 0.036,
  "earningIndex" : 0.30
}, {
  "rank" : 106,
  "name" : "ビーチパトロール",
  "birthYear" : 2013,
  "color" : "黒鹿毛",
  "origin" : "米",
  "runners" : 19,
  "winners" : 0,
  "starts" : 26,
  "wins" : 0,
  "prize" : 15296000,
  "prizePerStart" : 588308,
  "prizePerHorse" : 805053,
  "winRate" : 0.000,
  "earningIndex" : 0.45
}, {
  "rank" : 107,
  "name" : "Tapit",
  "birthYear" : 2001,
  "color" : "",
  "origin" : "米",
  "runners" : 3,
  "winners" : 2,
  "starts" : 3,
  "wins" : 2,
  "prize" : 15290000,
  "prizePerStart" : 5096667,
  "prizePerHorse" : 5096667,
  "winRate" : 0.667,
  "earningIndex" : 2.84
}, {
  "rank" : 108,
  "name" : "バンドワゴン",
  "birthYear" : 2011,
  "color" : "黒鹿毛",
  "origin" : "安平町",
  "runners" : 4,
  "winners" : 2,
  "starts" : 6,
  "wins" : 2,
  "prize" : 14800000,
  "prizePerStart" : 2466667,
  "prizePerHorse" : 3700000,
  "winRate" : 0.500,
  "earningIndex" : 2.06
}, {
  "rank" : 109,
  "name" : "Too Darn Hot",
  "birthYear" : 2016,
  "color" : "",
  "origin" : "英",
  "runners" : 1,
  "winners" : 1,
  "starts" : 2,
  "wins" : 1,
  "prize" : 14700000,
  "prizePerStart" : 7350000,
  "prizePerHorse" : 14700000,
  "winRate" : 1.000,
  "earningIndex" : 8.20
}, {
  "rank" : 110,
  "name" : "キンシャサノキセキ",
  "birthYear" : 2003,
  "color" : "鹿毛",
  "origin" : "豪",
  "runners" : 14,
  "winners" : 1,
  "starts" : 17,
  "wins" : 1,
  "prize" : 14440000,
  "prizePerStart" : 849412,
  "prizePerHorse" : 1031429,
  "winRate" : 0.071,
  "earningIndex" : 0.58
}, {
  "rank" : 111,
  "name" : "シュヴァルグラン",
  "birthYear" : 2012,
  "color" : "栗毛",
  "origin" : "安平町",
  "runners" : 21,
  "winners" : 0,
  "starts" : 24,
  "wins" : 0,
  "prize" : 14400000,
  "prizePerStart" : 600000,
  "prizePerHorse" : 685714,
  "winRate" : 0.000,
  "earningIndex" : 0.38
}, {
  "rank" : 112,
  "name" : "レッドファルクス",
  "birthYear" : 2011,
  "color" : "芦毛",
  "origin" : "千歳市",
  "runners" : 19,
  "winners" : 1,
  "starts" : 25,
  "wins" : 1,
  "prize" : 13860000,
  "prizePerStart" : 554400,
  "prizePerHorse" : 729474,
  "winRate" : 0.053,
  "earningIndex" : 0.41
}, {
  "rank" : 113,
  "name" : "ロージズインメイ",
  "birthYear" : 2000,
  "color" : "青鹿毛",
  "origin" : "米",
  "runners" : 5,
  "winners" : 0,
  "starts" : 9,
  "wins" : 0,
  "prize" : 13229000,
  "prizePerStart" : 1469889,
  "prizePerHorse" : 2645800,
  "winRate" : 0.000,
  "earningIndex" : 1.48
}, {
  "rank" : 114,
  "name" : "Liam's Map",
  "birthYear" : 2011,
  "color" : "",
  "origin" : "",
  "runners" : 5,
  "winners" : 1,
  "starts" : 5,
  "wins" : 1,
  "prize" : 13090000,
  "prizePerStart" : 2618000,
  "prizePerHorse" : 2618000,
  "winRate" : 0.200,
  "earningIndex" : 1.46
}, {
  "rank" : 115,
  "name" : "ノヴェリスト",
  "birthYear" : 2009,
  "color" : "黒鹿毛",
  "origin" : "愛",
  "runners" : 9,
  "winners" : 0,
  "starts" : 11,
  "wins" : 0,
  "prize" : 11764000,
  "prizePerStart" : 1069455,
  "prizePerHorse" : 1307111,
  "winRate" : 0.000,
  "earningIndex" : 0.73
}, {
  "rank" : 116,
  "name" : "ヴィクトワールピサ",
  "birthYear" : 2007,
  "color" : "黒鹿毛",
  "origin" : "千歳市",
  "runners" : 11,
  "winners" : 1,
  "starts" : 11,
  "wins" : 1,
  "prize" : 11500000,
  "prizePerStart" : 1045455,
  "prizePerHorse" : 1045455,
  "winRate" : 0.091,
  "earningIndex" : 0.58
}, {
  "rank" : 117,
  "name" : "ディープブリランテ",
  "birthYear" : 2009,
  "color" : "鹿毛",
  "origin" : "新冠町",
  "runners" : 13,
  "winners" : 0,
  "starts" : 20,
  "wins" : 0,
  "prize" : 10550000,
  "prizePerStart" : 527500,
  "prizePerHorse" : 811538,
  "winRate" : 0.000,
  "earningIndex" : 0.45
}, {
  "rank" : 118,
  "name" : "ワールドエース",
  "birthYear" : 2009,
  "color" : "鹿毛",
  "origin" : "安平町",
  "runners" : 7,
  "winners" : 0,
  "starts" : 9,
  "wins" : 0,
  "prize" : 9920000,
  "prizePerStart" : 1102222,
  "prizePerHorse" : 1417143,
  "winRate" : 0.000,
  "earningIndex" : 0.79
}, {
  "rank" : 119,
  "name" : "トゥザワールド",
  "birthYear" : 2011,
  "color" : "鹿毛",
  "origin" : "安平町",
  "runners" : 4,
  "winners" : 0,
  "starts" : 7,
  "wins" : 0,
  "prize" : 9549000,
  "prizePerStart" : 1364143,
  "prizePerHorse" : 2387250,
  "winRate" : 0.000,
  "earningIndex" : 1.33
}, {
  "rank" : 120,
  "name" : "Omaha Beach",
  "birthYear" : 2016,
  "color" : "",
  "origin" : "",
  "runners" : 3,
  "winners" : 1,
  "starts" : 4,
  "wins" : 1,
  "prize" : 9200000,
  "prizePerStart" : 2300000,
  "prizePerHorse" : 3066667,
  "winRate" : 0.333,
  "earningIndex" : 1.71
}, {
  "rank" : 121,
  "name" : "Tiz the Law",
  "birthYear" : 2017,
  "color" : "",
  "origin" : "",
  "runners" : 4,
  "winners" : 1,
  "starts" : 4,
  "wins" : 1,
  "prize" : 9020000,
  "prizePerStart" : 2255000,
  "prizePerHorse" : 2255000,
  "winRate" : 0.250,
  "earningIndex" : 1.26
}, {
  "rank" : 122,
  "name" : "Shancelot",
  "birthYear" : 2016,
  "color" : "鹿毛",
  "origin" : "",
  "runners" : 1,
  "winners" : 0,
  "starts" : 1,
  "wins" : 0,
  "prize" : 8906000,
  "prizePerStart" : 8906000,
  "prizePerHorse" : 8906000,
  "winRate" : 0.000,
  "earningIndex" : 4.97
}, {
  "rank" : 123,
  "name" : "ロゴタイプ",
  "birthYear" : 2010,
  "color" : "黒鹿毛",
  "origin" : "千歳市",
  "runners" : 14,
  "winners" : 0,
  "starts" : 16,
  "wins" : 0,
  "prize" : 8500000,
  "prizePerStart" : 531250,
  "prizePerHorse" : 607143,
  "winRate" : 0.000,
  "earningIndex" : 0.34
}, {
  "rank" : 124,
  "name" : "Adios Charlie",
  "birthYear" : 2008,
  "color" : "",
  "origin" : "",
  "runners" : 1,
  "winners" : 1,
  "starts" : 1,
  "wins" : 1,
  "prize" : 8200000,
  "prizePerStart" : 8200000,
  "prizePerHorse" : 8200000,
  "winRate" : 1.000,
  "earningIndex" : 4.57
}, {
  "rank" : 124,
  "name" : "American Pharoah",
  "birthYear" : 2012,
  "color" : "",
  "origin" : "米",
  "runners" : 12,
  "winners" : 1,
  "starts" : 14,
  "wins" : 1,
  "prize" : 8200000,
  "prizePerStart" : 585714,
  "prizePerHorse" : 683333,
  "winRate" : 0.083,
  "earningIndex" : 0.38
}, {
  "rank" : 124,
  "name" : "City of Light",
  "birthYear" : 2014,
  "color" : "",
  "origin" : "",
  "runners" : 2,
  "winners" : 1,
  "starts" : 2,
  "wins" : 1,
  "prize" : 8200000,
  "prizePerStart" : 4100000,
  "prizePerHorse" : 4100000,
  "winRate" : 0.500,
  "earningIndex" : 2.29
}, {
  "rank" : 124,
  "name" : "Exceedance",
  "birthYear" : 2016,
  "color" : "鹿毛",
  "origin" : "",
  "runners" : 1,
  "winners" : 1,
  "starts" : 1,
  "wins" : 1,
  "prize" : 8200000,
  "prizePerStart" : 8200000,
  "prizePerHorse" : 8200000,
  "winRate" : 1.000,
  "earningIndex" : 4.57
}, {
  "rank" : 128,
  "name" : "ウォータービルド",
  "birthYear" : 2014,
  "color" : "鹿毛",
  "origin" : "浦河町",
  "runners" : 5,
  "winners" : 0,
  "starts" : 9,
  "wins" : 0,
  "prize" : 8170000,
  "prizePerStart" : 907778,
  "prizePerHorse" : 1634000,
  "winRate" : 0.000,
  "earningIndex" : 0.91
}, {
  "rank" : 129,
  "name" : "Kantharos",
  "birthYear" : 2008,
  "color" : "",
  "origin" : "",
  "runners" : 1,
  "winners" : 0,
  "starts" : 2,
  "wins" : 0,
  "prize" : 7800000,
  "prizePerStart" : 3900000,
  "prizePerHorse" : 7800000,
  "winRate" : 0.000,
  "earningIndex" : 4.35
}, {
  "rank" : 130,
  "name" : "ノーブルミッション",
  "birthYear" : 2009,
  "color" : "鹿毛",
  "origin" : "英",
  "runners" : 11,
  "winners" : 0,
  "starts" : 13,
  "wins" : 0,
  "prize" : 7586000,
  "prizePerStart" : 583538,
  "prizePerHorse" : 689636,
  "winRate" : 0.000,
  "earningIndex" : 0.38
}, {
  "rank" : 131,
  "name" : "キセキ",
  "birthYear" : 2014,
  "color" : "黒鹿毛",
  "origin" : "日高町",
  "runners" : 19,
  "winners" : 0,
  "starts" : 27,
  "wins" : 0,
  "prize" : 7560000,
  "prizePerStart" : 280000,
  "prizePerHorse" : 397895,
  "winRate" : 0.000,
  "earningIndex" : 0.22
}, {
  "rank" : 132,
  "name" : "ゴールドアクター",
  "birthYear" : 2011,
  "color" : "青鹿毛",
  "origin" : "新冠町",
  "runners" : 12,
  "winners" : 0,
  "starts" : 14,
  "wins" : 0,
  "prize" : 7543000,
  "prizePerStart" : 538786,
  "prizePerHorse" : 628583,
  "winRate" : 0.000,
  "earningIndex" : 0.35
}, {
  "rank" : 133,
  "name" : "エイシンフラッシュ",
  "birthYear" : 2007,
  "color" : "黒鹿毛",
  "origin" : "千歳市",
  "runners" : 12,
  "winners" : 0,
  "starts" : 15,
  "wins" : 0,
  "prize" : 7410000,
  "prizePerStart" : 494000,
  "prizePerHorse" : 617500,
  "winRate" : 0.000,
  "earningIndex" : 0.34
}, {
  "rank" : 134,
  "name" : "グァンチャーレ",
  "birthYear" : 2012,
  "color" : "青鹿毛",
  "origin" : "新冠町",
  "runners" : 3,
  "winners" : 1,
  "starts" : 4,
  "wins" : 1,
  "prize" : 7320000,
  "prizePerStart" : 1830000,
  "prizePerHorse" : 2440000,
  "winRate" : 0.333,
  "earningIndex" : 1.36
}, {
  "rank" : 135,
  "name" : "Constitution",
  "birthYear" : 2011,
  "color" : "",
  "origin" : "",
  "runners" : 3,
  "winners" : 0,
  "starts" : 3,
  "wins" : 0,
  "prize" : 7145000,
  "prizePerStart" : 2381667,
  "prizePerHorse" : 2381667,
  "winRate" : 0.000,
  "earningIndex" : 1.33
}, {
  "rank" : 136,
  "name" : "ダノンキングリー",
  "birthYear" : 2016,
  "color" : "黒鹿毛",
  "origin" : "浦河町",
  "runners" : 15,
  "winners" : 1,
  "starts" : 18,
  "wins" : 1,
  "prize" : 7140000,
  "prizePerStart" : 396667,
  "prizePerHorse" : 476000,
  "winRate" : 0.067,
  "earningIndex" : 0.27
}, {
  "rank" : 137,
  "name" : "リーチザクラウン",
  "birthYear" : 2006,
  "color" : "青鹿毛",
  "origin" : "千歳市",
  "runners" : 9,
  "winners" : 0,
  "starts" : 10,
  "wins" : 0,
  "prize" : 6870000,
  "prizePerStart" : 687000,
  "prizePerHorse" : 763333,
  "winRate" : 0.000,
  "earningIndex" : 0.43
}, {
  "rank" : 138,
  "name" : "No Nay Never",
  "birthYear" : 2011,
  "color" : "",
  "origin" : "米",
  "runners" : 4,
  "winners" : 0,
  "starts" : 4,
  "wins" : 0,
  "prize" : 6670000,
  "prizePerStart" : 1667500,
  "prizePerHorse" : 1667500,
  "winRate" : 0.000,
  "earningIndex" : 0.93
}, {
  "rank" : 139,
  "name" : "Mitole",
  "birthYear" : 2015,
  "color" : "",
  "origin" : "",
  "runners" : 1,
  "winners" : 0,
  "starts" : 2,
  "wins" : 0,
  "prize" : 6600000,
  "prizePerStart" : 3300000,
  "prizePerHorse" : 6600000,
  "winRate" : 0.000,
  "earningIndex" : 3.68
}, {
  "rank" : 140,
  "name" : "I Am Invincible",
  "birthYear" : 2004,
  "color" : "",
  "origin" : "",
  "runners" : 1,
  "winners" : 1,
  "starts" : 1,
  "wins" : 1,
  "prize" : 6500000,
  "prizePerStart" : 6500000,
  "prizePerHorse" : 6500000,
  "winRate" : 1.000,
  "earningIndex" : 3.63
}, {
  "rank" : 140,
  "name" : "Improbable",
  "birthYear" : 2016,
  "color" : "",
  "origin" : "",
  "runners" : 1,
  "winners" : 1,
  "starts" : 1,
  "wins" : 1,
  "prize" : 6500000,
  "prizePerStart" : 6500000,
  "prizePerHorse" : 6500000,
  "winRate" : 1.000,
  "earningIndex" : 3.63
}, {
  "rank" : 140,
  "name" : "インカンテーション",
  "birthYear" : 2010,
  "color" : "鹿毛",
  "origin" : "浦河町",
  "runners" : 4,
  "winners" : 1,
  "starts" : 4,
  "wins" : 1,
  "prize" : 6500000,
  "prizePerStart" : 1625000,
  "prizePerHorse" : 1625000,
  "winRate" : 0.250,
  "earningIndex" : 0.91
}, {
  "rank" : 143,
  "name" : "Nyquist",
  "birthYear" : 2013,
  "color" : "",
  "origin" : "",
  "runners" : 2,
  "winners" : 1,
  "starts" : 2,
  "wins" : 1,
  "prize" : 5900000,
  "prizePerStart" : 2950000,
  "prizePerHorse" : 2950000,
  "winRate" : 0.500,
  "earningIndex" : 1.65
}, {
  "rank" : 143,
  "name" : "St Mark's Basilica",
  "birthYear" : 2018,
  "color" : "",
  "origin" : "仏",
  "runners" : 2,
  "winners" : 1,
  "starts" : 2,
  "wins" : 1,
  "prize" : 5900000,
  "prizePerStart" : 2950000,
  "prizePerHorse" : 2950000,
  "winRate" : 0.500,
  "earningIndex" : 1.65
}, {
  "rank" : 143,
  "name" : "Vino Rosso",
  "birthYear" : 2015,
  "color" : "",
  "origin" : "",
  "runners" : 2,
  "winners" : 1,
  "starts" : 3,
  "wins" : 1,
  "prize" : 5900000,
  "prizePerStart" : 1966667,
  "prizePerHorse" : 2950000,
  "winRate" : 0.500,
  "earningIndex" : 1.65
}, {
  "rank" : 143,
  "name" : "ワールドプレミア",
  "birthYear" : 2016,
  "color" : "黒鹿毛",
  "origin" : "安平町",
  "runners" : 6,
  "winners" : 1,
  "starts" : 7,
  "wins" : 1,
  "prize" : 5900000,
  "prizePerStart" : 842857,
  "prizePerHorse" : 983333,
  "winRate" : 0.167,
  "earningIndex" : 0.55
}, {
  "rank" : 147,
  "name" : "トランセンド",
  "birthYear" : 2006,
  "color" : "鹿毛",
  "origin" : "新冠町",
  "runners" : 7,
  "winners" : 0,
  "starts" : 10,
  "wins" : 0,
  "prize" : 5880000,
  "prizePerStart" : 588000,
  "prizePerHorse" : 840000,
  "winRate" : 0.000,
  "earningIndex" : 0.47
}, {
  "rank" : 148,
  "name" : "Golden Horn",
  "birthYear" : 2012,
  "color" : "",
  "origin" : "",
  "runners" : 2,
  "winners" : 0,
  "starts" : 3,
  "wins" : 0,
  "prize" : 5520000,
  "prizePerStart" : 1840000,
  "prizePerHorse" : 2760000,
  "winRate" : 0.000,
  "earningIndex" : 1.54
}, {
  "rank" : 149,
  "name" : "ストロングリターン",
  "birthYear" : 2006,
  "color" : "鹿毛",
  "origin" : "千歳市",
  "runners" : 11,
  "winners" : 0,
  "starts" : 11,
  "wins" : 0,
  "prize" : 4810000,
  "prizePerStart" : 437273,
  "prizePerHorse" : 437273,
  "winRate" : 0.000,
  "earningIndex" : 0.24
}, {
  "rank" : 150,
  "name" : "メイショウサムソン",
  "birthYear" : 2003,
  "color" : "鹿毛",
  "origin" : "浦河町",
  "runners" : 3,
  "winners" : 0,
  "starts" : 3,
  "wins" : 0,
  "prize" : 4752000,
  "prizePerStart" : 1584000,
  "prizePerHorse" : 1584000,
  "winRate" : 0.000,
  "earningIndex" : 0.88
}, {
  "rank" : 151,
  "name" : "アポロケンタッキー",
  "birthYear" : 2012,
  "color" : "鹿毛",
  "origin" : "米",
  "runners" : 6,
  "winners" : 0,
  "starts" : 11,
  "wins" : 0,
  "prize" : 4480000,
  "prizePerStart" : 407273,
  "prizePerHorse" : 746667,
  "winRate" : 0.000,
  "earningIndex" : 0.42
}, {
  "rank" : 152,
  "name" : "Quality Road",
  "birthYear" : 2006,
  "color" : "",
  "origin" : "米",
  "runners" : 3,
  "winners" : 0,
  "starts" : 7,
  "wins" : 0,
  "prize" : 4200000,
  "prizePerStart" : 600000,
  "prizePerHorse" : 1400000,
  "winRate" : 0.000,
  "earningIndex" : 0.78
}, {
  "rank" : 153,
  "name" : "アポロキングダム",
  "birthYear" : 2003,
  "color" : "栗毛",
  "origin" : "米",
  "runners" : 4,
  "winners" : 0,
  "starts" : 6,
  "wins" : 0,
  "prize" : 4036000,
  "prizePerStart" : 672667,
  "prizePerHorse" : 1009000,
  "winRate" : 0.000,
  "earningIndex" : 0.56
}, {
  "rank" : 154,
  "name" : "Le Havre",
  "birthYear" : 2006,
  "color" : "",
  "origin" : "愛",
  "runners" : 1,
  "winners" : 0,
  "starts" : 1,
  "wins" : 0,
  "prize" : 4035000,
  "prizePerStart" : 4035000,
  "prizePerHorse" : 4035000,
  "winRate" : 0.000,
  "earningIndex" : 2.25
}, {
  "rank" : 155,
  "name" : "ヴァンゴッホ",
  "birthYear" : 2018,
  "color" : "鹿毛",
  "origin" : "米",
  "runners" : 14,
  "winners" : 0,
  "starts" : 18,
  "wins" : 0,
  "prize" : 4020000,
  "prizePerStart" : 223333,
  "prizePerHorse" : 287143,
  "winRate" : 0.000,
  "earningIndex" : 0.16
}, {
  "rank" : 156,
  "name" : "ネオユニヴァース",
  "birthYear" : 2000,
  "color" : "鹿毛",
  "origin" : "千歳市",
  "runners" : 4,
  "winners" : 0,
  "starts" : 5,
  "wins" : 0,
  "prize" : 4010000,
  "prizePerStart" : 802000,
  "prizePerHorse" : 1002500,
  "winRate" : 0.000,
  "earningIndex" : 0.56
}, {
  "rank" : 157,
  "name" : "アドマイヤムーン",
  "birthYear" : 2003,
  "color" : "鹿毛",
  "origin" : "早来町",
  "runners" : 8,
  "winners" : 0,
  "starts" : 9,
  "wins" : 0,
  "prize" : 3700000,
  "prizePerStart" : 411111,
  "prizePerHorse" : 462500,
  "winRate" : 0.000,
  "earningIndex" : 0.26
}, {
  "rank" : 158,
  "name" : "Dansili",
  "birthYear" : 1996,
  "color" : "",
  "origin" : "英",
  "runners" : 1,
  "winners" : 0,
  "starts" : 1,
  "wins" : 0,
  "prize" : 3600000,
  "prizePerStart" : 3600000,
  "prizePerHorse" : 3600000,
  "winRate" : 0.000,
  "earningIndex" : 2.01
}, {
  "rank" : 158,
  "name" : "Practical Joke",
  "birthYear" : 2014,
  "color" : "",
  "origin" : "米",
  "runners" : 6,
  "winners" : 0,
  "starts" : 6,
  "wins" : 0,
  "prize" : 3600000,
  "prizePerStart" : 600000,
  "prizePerHorse" : 600000,
  "winRate" : 0.000,
  "earningIndex" : 0.33
}, {
  "rank" : 158,
  "name" : "ドリームジャーニー",
  "birthYear" : 2004,
  "color" : "鹿毛",
  "origin" : "白老町",
  "runners" : 3,
  "winners" : 0,
  "starts" : 3,
  "wins" : 0,
  "prize" : 3600000,
  "prizePerStart" : 1200000,
  "prizePerHorse" : 1200000,
  "winRate" : 0.000,
  "earningIndex" : 0.67
}, {
  "rank" : 161,
  "name" : "オウケンワールド",
  "birthYear" : 2012,
  "color" : "芦毛",
  "origin" : "浦河町",
  "runners" : 1,
  "winners" : 0,
  "starts" : 2,
  "wins" : 0,
  "prize" : 3380000,
  "prizePerStart" : 1690000,
  "prizePerHorse" : 3380000,
  "winRate" : 0.000,
  "earningIndex" : 1.89
}, {
  "rank" : 162,
  "name" : "Bolt d'Oro",
  "birthYear" : 2015,
  "color" : "",
  "origin" : "米",
  "runners" : 3,
  "winners" : 0,
  "starts" : 3,
  "wins" : 0,
  "prize" : 3300000,
  "prizePerStart" : 1100000,
  "prizePerHorse" : 1100000,
  "winRate" : 0.000,
  "earningIndex" : 0.61
}, {
  "rank" : 162,
  "name" : "エスケンデレヤ",
  "birthYear" : 2007,
  "color" : "栗毛",
  "origin" : "米",
  "runners" : 5,
  "winners" : 0,
  "starts" : 6,
  "wins" : 0,
  "prize" : 3300000,
  "prizePerStart" : 550000,
  "prizePerHorse" : 660000,
  "winRate" : 0.000,
  "earningIndex" : 0.37
}, {
  "rank" : 162,
  "name" : "バトルプラン",
  "birthYear" : 2005,
  "color" : "鹿毛",
  "origin" : "米",
  "runners" : 3,
  "winners" : 0,
  "starts" : 3,
  "wins" : 0,
  "prize" : 3300000,
  "prizePerStart" : 1100000,
  "prizePerHorse" : 1100000,
  "winRate" : 0.000,
  "earningIndex" : 0.61
}, {
  "rank" : 162,
  "name" : "マルターズアポジー",
  "birthYear" : 2012,
  "color" : "鹿毛",
  "origin" : "新冠町",
  "runners" : 1,
  "winners" : 0,
  "starts" : 1,
  "wins" : 0,
  "prize" : 3300000,
  "prizePerStart" : 3300000,
  "prizePerHorse" : 3300000,
  "winRate" : 0.000,
  "earningIndex" : 1.84
}, {
  "rank" : 162,
  "name" : "ヴァンセンヌ",
  "birthYear" : 2009,
  "color" : "鹿毛",
  "origin" : "白老町",
  "runners" : 7,
  "winners" : 0,
  "starts" : 7,
  "wins" : 0,
  "prize" : 3300000,
  "prizePerStart" : 471429,
  "prizePerHorse" : 471429,
  "winRate" : 0.000,
  "earningIndex" : 0.26
}, {
  "rank" : 167,
  "name" : "Mendelssohn",
  "birthYear" : 2015,
  "color" : "",
  "origin" : "米",
  "runners" : 1,
  "winners" : 0,
  "starts" : 2,
  "wins" : 0,
  "prize" : 3290000,
  "prizePerStart" : 1645000,
  "prizePerHorse" : 3290000,
  "winRate" : 0.000,
  "earningIndex" : 1.84
}, {
  "rank" : 168,
  "name" : "サングレーザー",
  "birthYear" : 2014,
  "color" : "青鹿毛",
  "origin" : "安平町",
  "runners" : 2,
  "winners" : 0,
  "starts" : 4,
  "wins" : 0,
  "prize" : 3000000,
  "prizePerStart" : 750000,
  "prizePerHorse" : 1500000,
  "winRate" : 0.000,
  "earningIndex" : 0.84
}, {
  "rank" : 168,
  "name" : "ヴァンキッシュラン",
  "birthYear" : 2013,
  "color" : "黒鹿毛",
  "origin" : "千歳市",
  "runners" : 1,
  "winners" : 0,
  "starts" : 1,
  "wins" : 0,
  "prize" : 3000000,
  "prizePerStart" : 3000000,
  "prizePerHorse" : 3000000,
  "winRate" : 0.000,
  "earningIndex" : 1.67
}, {
  "rank" : 170,
  "name" : "ラニ",
  "birthYear" : 2013,
  "color" : "芦毛",
  "origin" : "米",
  "runners" : 5,
  "winners" : 0,
  "starts" : 6,
  "wins" : 0,
  "prize" : 2840000,
  "prizePerStart" : 473333,
  "prizePerHorse" : 568000,
  "winRate" : 0.000,
  "earningIndex" : 0.32
}, {
  "rank" : 171,
  "name" : "Snitzel",
  "birthYear" : 2002,
  "color" : "",
  "origin" : "",
  "runners" : 1,
  "winners" : 0,
  "starts" : 2,
  "wins" : 0,
  "prize" : 2800000,
  "prizePerStart" : 1400000,
  "prizePerHorse" : 2800000,
  "winRate" : 0.000,
  "earningIndex" : 1.56
}, {
  "rank" : 172,
  "name" : "Night of Thunder",
  "birthYear" : 2011,
  "color" : "",
  "origin" : "愛",
  "runners" : 1,
  "winners" : 0,
  "starts" : 1,
  "wins" : 0,
  "prize" : 2600000,
  "prizePerStart" : 2600000,
  "prizePerHorse" : 2600000,
  "winRate" : 0.000,
  "earningIndex" : 1.45
}, {
  "rank" : 172,
  "name" : "バンブーエール",
  "birthYear" : 2003,
  "color" : "栗毛",
  "origin" : "浦河町",
  "runners" : 2,
  "winners" : 0,
  "starts" : 2,
  "wins" : 0,
  "prize" : 2600000,
  "prizePerStart" : 1300000,
  "prizePerHorse" : 1300000,
  "winRate" : 0.000,
  "earningIndex" : 0.73
}, {
  "rank" : 174,
  "name" : "Mo Town",
  "birthYear" : 2014,
  "color" : "",
  "origin" : "",
  "runners" : 1,
  "winners" : 0,
  "starts" : 1,
  "wins" : 0,
  "prize" : 2400000,
  "prizePerStart" : 2400000,
  "prizePerHorse" : 2400000,
  "winRate" : 0.000,
  "earningIndex" : 1.34
}, {
  "rank" : 174,
  "name" : "グランデッツァ",
  "birthYear" : 2009,
  "color" : "栗毛",
  "origin" : "千歳市",
  "runners" : 1,
  "winners" : 0,
  "starts" : 1,
  "wins" : 0,
  "prize" : 2400000,
  "prizePerStart" : 2400000,
  "prizePerHorse" : 2400000,
  "winRate" : 0.000,
  "earningIndex" : 1.34
}, {
  "rank" : 174,
  "name" : "マンハッタンカフェ",
  "birthYear" : 1998,
  "color" : "青鹿毛",
  "origin" : "千歳市",
  "runners" : 1,
  "winners" : 0,
  "starts" : 1,
  "wins" : 0,
  "prize" : 2400000,
  "prizePerStart" : 2400000,
  "prizePerHorse" : 2400000,
  "winRate" : 0.000,
  "earningIndex" : 1.34
}, {
  "rank" : 177,
  "name" : "ネロ",
  "birthYear" : 2011,
  "color" : "栗毛",
  "origin" : "新ひだか町",
  "runners" : 6,
  "winners" : 0,
  "starts" : 8,
  "wins" : 0,
  "prize" : 2390000,
  "prizePerStart" : 298750,
  "prizePerHorse" : 398333,
  "winRate" : 0.000,
  "earningIndex" : 0.22
}, {
  "rank" : 178,
  "name" : "リオンリオン",
  "birthYear" : 2016,
  "color" : "鹿毛",
  "origin" : "安平町",
  "runners" : 5,
  "winners" : 0,
  "starts" : 7,
  "wins" : 0,
  "prize" : 2290000,
  "prizePerStart" : 327143,
  "prizePerHorse" : 458000,
  "winRate" : 0.000,
  "earningIndex" : 0.26
}, {
  "rank" : 179,
  "name" : "サウスヴィグラス",
  "birthYear" : 1996,
  "color" : "栗毛",
  "origin" : "米",
  "runners" : 2,
  "winners" : 0,
  "starts" : 2,
  "wins" : 0,
  "prize" : 2100000,
  "prizePerStart" : 1050000,
  "prizePerHorse" : 1050000,
  "winRate" : 0.000,
  "earningIndex" : 0.59
}, {
  "rank" : 179,
  "name" : "ナムラタイタン",
  "birthYear" : 2006,
  "color" : "栗毛",
  "origin" : "新ひだか町",
  "runners" : 1,
  "winners" : 0,
  "starts" : 1,
  "wins" : 0,
  "prize" : 2100000,
  "prizePerStart" : 2100000,
  "prizePerHorse" : 2100000,
  "winRate" : 0.000,
  "earningIndex" : 1.17
}, {
  "rank" : 179,
  "name" : "モンテロッソ",
  "birthYear" : 2007,
  "color" : "鹿毛",
  "origin" : "英",
  "runners" : 1,
  "winners" : 0,
  "starts" : 1,
  "wins" : 0,
  "prize" : 2100000,
  "prizePerStart" : 2100000,
  "prizePerHorse" : 2100000,
  "winRate" : 0.000,
  "earningIndex" : 1.17
}, {
  "rank" : 179,
  "name" : "レインボーライン",
  "birthYear" : 2013,
  "color" : "鹿毛",
  "origin" : "安平町",
  "runners" : 3,
  "winners" : 0,
  "starts" : 3,
  "wins" : 0,
  "prize" : 2100000,
  "prizePerStart" : 700000,
  "prizePerHorse" : 700000,
  "winRate" : 0.000,
  "earningIndex" : 0.39
}, {
  "rank" : 183,
  "name" : "ケープブランコ",
  "birthYear" : 2007,
  "color" : "栗毛",
  "origin" : "愛",
  "runners" : 2,
  "winners" : 0,
  "starts" : 2,
  "wins" : 0,
  "prize" : 1870000,
  "prizePerStart" : 935000,
  "prizePerHorse" : 935000,
  "winRate" : 0.000,
  "earningIndex" : 0.52
}, {
  "rank" : 184,
  "name" : "City Zip",
  "birthYear" : 1998,
  "color" : "",
  "origin" : "米",
  "runners" : 1,
  "winners" : 0,
  "starts" : 2,
  "wins" : 0,
  "prize" : 1800000,
  "prizePerStart" : 900000,
  "prizePerHorse" : 1800000,
  "winRate" : 0.000,
  "earningIndex" : 1.00
}, {
  "rank" : 185,
  "name" : "ホークビル",
  "birthYear" : 2013,
  "color" : "栗毛",
  "origin" : "米",
  "runners" : 5,
  "winners" : 0,
  "starts" : 7,
  "wins" : 0,
  "prize" : 1780000,
  "prizePerStart" : 254286,
  "prizePerHorse" : 356000,
  "winRate" : 0.000,
  "earningIndex" : 0.20
}, {
  "rank" : 186,
  "name" : "サトノジェネシス",
  "birthYear" : 2016,
  "color" : "鹿毛",
  "origin" : "安平町",
  "runners" : 7,
  "winners" : 0,
  "starts" : 8,
  "wins" : 0,
  "prize" : 1600000,
  "prizePerStart" : 200000,
  "prizePerHorse" : 228571,
  "winRate" : 0.000,
  "earningIndex" : 0.13
}, {
  "rank" : 187,
  "name" : "Dark Angel",
  "birthYear" : 2005,
  "color" : "",
  "origin" : "愛",
  "runners" : 3,
  "winners" : 0,
  "starts" : 3,
  "wins" : 0,
  "prize" : 1500000,
  "prizePerStart" : 500000,
  "prizePerHorse" : 500000,
  "winRate" : 0.000,
  "earningIndex" : 0.28
}, {
  "rank" : 187,
  "name" : "Maclean's Music",
  "birthYear" : 2008,
  "color" : "",
  "origin" : "",
  "runners" : 3,
  "winners" : 0,
  "starts" : 3,
  "wins" : 0,
  "prize" : 1500000,
  "prizePerStart" : 500000,
  "prizePerHorse" : 500000,
  "winRate" : 0.000,
  "earningIndex" : 0.28
}, {
  "rank" : 187,
  "name" : "カフジテイク",
  "birthYear" : 2012,
  "color" : "青鹿毛",
  "origin" : "浦河町",
  "runners" : 1,
  "winners" : 0,
  "starts" : 1,
  "wins" : 0,
  "prize" : 1500000,
  "prizePerStart" : 1500000,
  "prizePerHorse" : 1500000,
  "winRate" : 0.000,
  "earningIndex" : 0.84
}, {
  "rank" : 190,
  "name" : "クラウンレガーロ",
  "birthYear" : 2010,
  "color" : "栗毛",
  "origin" : "新冠町",
  "runners" : 2,
  "winners" : 0,
  "starts" : 3,
  "wins" : 0,
  "prize" : 1480000,
  "prizePerStart" : 493333,
  "prizePerHorse" : 740000,
  "winRate" : 0.000,
  "earningIndex" : 0.41
}, {
  "rank" : 191,
  "name" : "Study of Man",
  "birthYear" : 2015,
  "color" : "",
  "origin" : "愛",
  "runners" : 1,
  "winners" : 0,
  "starts" : 1,
  "wins" : 0,
  "prize" : 1300000,
  "prizePerStart" : 1300000,
  "prizePerHorse" : 1300000,
  "winRate" : 0.000,
  "earningIndex" : 0.73
}, {
  "rank" : 191,
  "name" : "ヤマニンセラフィム",
  "birthYear" : 1999,
  "color" : "栗毛",
  "origin" : "新冠町",
  "runners" : 1,
  "winners" : 0,
  "starts" : 1,
  "wins" : 0,
  "prize" : 1300000,
  "prizePerStart" : 1300000,
  "prizePerHorse" : 1300000,
  "winRate" : 0.000,
  "earningIndex" : 0.73
}, {
  "rank" : 193,
  "name" : "エポカドーロ",
  "birthYear" : 2015,
  "color" : "黒鹿毛",
  "origin" : "新ひだか町",
  "runners" : 4,
  "winners" : 0,
  "starts" : 6,
  "wins" : 0,
  "prize" : 1200000,
  "prizePerStart" : 200000,
  "prizePerHorse" : 300000,
  "winRate" : 0.000,
  "earningIndex" : 0.17
}, {
  "rank" : 193,
  "name" : "フェノーメノ",
  "birthYear" : 2009,
  "color" : "青鹿毛",
  "origin" : "平取町",
  "runners" : 2,
  "winners" : 0,
  "starts" : 3,
  "wins" : 0,
  "prize" : 1200000,
  "prizePerStart" : 400000,
  "prizePerHorse" : 600000,
  "winRate" : 0.000,
  "earningIndex" : 0.33
}, {
  "rank" : 195,
  "name" : "スピルバーグ",
  "birthYear" : 2009,
  "color" : "鹿毛",
  "origin" : "千歳市",
  "runners" : 5,
  "winners" : 0,
  "starts" : 5,
  "wins" : 0,
  "prize" : 840000,
  "prizePerStart" : 168000,
  "prizePerHorse" : 168000,
  "winRate" : 0.000,
  "earningIndex" : 0.09
}, {
  "rank" : 196,
  "name" : "Munnings",
  "birthYear" : 2006,
  "color" : "",
  "origin" : "米",
  "runners" : 2,
  "winners" : 0,
  "starts" : 3,
  "wins" : 0,
  "prize" : 820000,
  "prizePerStart" : 273333,
  "prizePerHorse" : 410000,
  "winRate" : 0.000,
  "earningIndex" : 0.23
}, {
  "rank" : 196,
  "name" : "アイファーソング",
  "birthYear" : 2008,
  "color" : "青毛",
  "origin" : "新ひだか町",
  "runners" : 2,
  "winners" : 0,
  "starts" : 2,
  "wins" : 0,
  "prize" : 820000,
  "prizePerStart" : 410000,
  "prizePerHorse" : 410000,
  "winRate" : 0.000,
  "earningIndex" : 0.23
}, {
  "rank" : 196,
  "name" : "アドミラブル",
  "birthYear" : 2014,
  "color" : "鹿毛",
  "origin" : "安平町",
  "runners" : 2,
  "winners" : 0,
  "starts" : 3,
  "wins" : 0,
  "prize" : 820000,
  "prizePerStart" : 273333,
  "prizePerHorse" : 410000,
  "winRate" : 0.000,
  "earningIndex" : 0.23
}, {
  "rank" : 196,
  "name" : "スマートファルコン",
  "birthYear" : 2005,
  "color" : "栗毛",
  "origin" : "静内町",
  "runners" : 4,
  "winners" : 0,
  "starts" : 8,
  "wins" : 0,
  "prize" : 820000,
  "prizePerStart" : 102500,
  "prizePerHorse" : 205000,
  "winRate" : 0.000,
  "earningIndex" : 0.11
}, {
  "rank" : 196,
  "name" : "トーホウジャッカル",
  "birthYear" : 2011,
  "color" : "栗毛",
  "origin" : "日高町",
  "runners" : 3,
  "winners" : 0,
  "starts" : 5,
  "wins" : 0,
  "prize" : 820000,
  "prizePerStart" : 164000,
  "prizePerHorse" : 273333,
  "winRate" : 0.000,
  "earningIndex" : 0.15
}, {
  "rank" : 196,
  "name" : "マクマホン",
  "birthYear" : 2014,
  "color" : "鹿毛",
  "origin" : "伊",
  "runners" : 3,
  "winners" : 0,
  "starts" : 4,
  "wins" : 0,
  "prize" : 820000,
  "prizePerStart" : 205000,
  "prizePerHorse" : 273333,
  "winRate" : 0.000,
  "earningIndex" : 0.15
}, {
  "rank" : 202,
  "name" : "Dragon Pulse",
  "birthYear" : 2009,
  "color" : "",
  "origin" : "",
  "runners" : 1,
  "winners" : 0,
  "starts" : 1,
  "wins" : 0,
  "prize" : 650000,
  "prizePerStart" : 650000,
  "prizePerHorse" : 650000,
  "winRate" : 0.000,
  "earningIndex" : 0.36
}, {
  "rank" : 202,
  "name" : "Wootton Bassett",
  "birthYear" : 2008,
  "color" : "",
  "origin" : "",
  "runners" : 2,
  "winners" : 0,
  "starts" : 2,
  "wins" : 0,
  "prize" : 650000,
  "prizePerStart" : 325000,
  "prizePerHorse" : 325000,
  "winRate" : 0.000,
  "earningIndex" : 0.18
}, {
  "rank" : 202,
  "name" : "アルバート",
  "birthYear" : 2011,
  "color" : "栗毛",
  "origin" : "安平町",
  "runners" : 3,
  "winners" : 0,
  "starts" : 3,
  "wins" : 0,
  "prize" : 650000,
  "prizePerStart" : 216667,
  "prizePerHorse" : 216667,
  "winRate" : 0.000,
  "earningIndex" : 0.12
}, {
  "rank" : 205,
  "name" : "Blame",
  "birthYear" : 2006,
  "color" : "",
  "origin" : "",
  "runners" : 2,
  "winners" : 0,
  "starts" : 3,
  "wins" : 0,
  "prize" : 590000,
  "prizePerStart" : 196667,
  "prizePerHorse" : 295000,
  "winRate" : 0.000,
  "earningIndex" : 0.16
}, {
  "rank" : 205,
  "name" : "McKinzie",
  "birthYear" : 2015,
  "color" : "",
  "origin" : "",
  "runners" : 1,
  "winners" : 0,
  "starts" : 1,
  "wins" : 0,
  "prize" : 590000,
  "prizePerStart" : 590000,
  "prizePerHorse" : 590000,
  "winRate" : 0.000,
  "earningIndex" : 0.33
}, {
  "rank" : 207,
  "name" : "Army Mule",
  "birthYear" : 2014,
  "color" : "",
  "origin" : "",
  "runners" : 1,
  "winners" : 0,
  "starts" : 1,
  "wins" : 0,
  "prize" : 0,
  "prizePerStart" : 0,
  "prizePerHorse" : 0,
  "winRate" : 0.000,
  "earningIndex" : 0.00
}, {
  "rank" : 207,
  "name" : "Arrogate",
  "birthYear" : 2013,
  "color" : "",
  "origin" : "米",
  "runners" : 1,
  "winners" : 0,
  "starts" : 1,
  "wins" : 0,
  "prize" : 0,
  "prizePerStart" : 0,
  "prizePerHorse" : 0,
  "winRate" : 0.000,
  "earningIndex" : 0.00
}, {
  "rank" : 207,
  "name" : "Australia",
  "birthYear" : 2011,
  "color" : "",
  "origin" : "",
  "runners" : 1,
  "winners" : 0,
  "starts" : 1,
  "wins" : 0,
  "prize" : 0,
  "prizePerStart" : 0,
  "prizePerHorse" : 0,
  "winRate" : 0.000,
  "earningIndex" : 0.00
}, {
  "rank" : 207,
  "name" : "Authentic",
  "birthYear" : 2017,
  "color" : "",
  "origin" : "",
  "runners" : 2,
  "winners" : 0,
  "starts" : 2,
  "wins" : 0,
  "prize" : 0,
  "prizePerStart" : 0,
  "prizePerHorse" : 0,
  "winRate" : 0.000,
  "earningIndex" : 0.00
}, {
  "rank" : 207,
  "name" : "Beau Liam",
  "birthYear" : 2018,
  "color" : "",
  "origin" : "",
  "runners" : 2,
  "winners" : 0,
  "starts" : 2,
  "wins" : 0,
  "prize" : 0,
  "prizePerStart" : 0,
  "prizePerHorse" : 0,
  "winRate" : 0.000,
  "earningIndex" : 0.00
}, {
  "rank" : 207,
  "name" : "Bernardini",
  "birthYear" : 2003,
  "color" : "",
  "origin" : "米",
  "runners" : 1,
  "winners" : 0,
  "starts" : 1,
  "wins" : 0,
  "prize" : 0,
  "prizePerStart" : 0,
  "prizePerHorse" : 0,
  "winRate" : 0.000,
  "earningIndex" : 0.00
}, {
  "rank" : 207,
  "name" : "Blue Point",
  "birthYear" : 2014,
  "color" : "",
  "origin" : "",
  "runners" : 2,
  "winners" : 0,
  "starts" : 2,
  "wins" : 0,
  "prize" : 0,
  "prizePerStart" : 0,
  "prizePerHorse" : 0,
  "winRate" : 0.000,
  "earningIndex" : 0.00
}, {
  "rank" : 207,
  "name" : "Cairo Prince",
  "birthYear" : 2011,
  "color" : "",
  "origin" : "米",
  "runners" : 1,
  "winners" : 0,
  "starts" : 1,
  "wins" : 0,
  "prize" : 0,
  "prizePerStart" : 0,
  "prizePerHorse" : 0,
  "winRate" : 0.000,
  "earningIndex" : 0.00
}, {
  "rank" : 207,
  "name" : "Cajun Breeze",
  "birthYear" : 2008,
  "color" : "",
  "origin" : "",
  "runners" : 1,
  "winners" : 0,
  "starts" : 1,
  "wins" : 0,
  "prize" : 0,
  "prizePerStart" : 0,
  "prizePerHorse" : 0,
  "winRate" : 0.000,
  "earningIndex" : 0.00
}, {
  "rank" : 207,
  "name" : "Caravaggio",
  "birthYear" : 2014,
  "color" : "",
  "origin" : "米",
  "runners" : 1,
  "winners" : 0,
  "starts" : 1,
  "wins" : 0,
  "prize" : 0,
  "prizePerStart" : 0,
  "prizePerHorse" : 0,
  "winRate" : 0.000,
  "earningIndex" : 0.00
}, {
  "rank" : 207,
  "name" : "Catholic Boy",
  "birthYear" : 2015,
  "color" : "",
  "origin" : "",
  "runners" : 1,
  "winners" : 0,
  "starts" : 2,
  "wins" : 0,
  "prize" : 0,
  "prizePerStart" : 0,
  "prizePerHorse" : 0,
  "winRate" : 0.000,
  "earningIndex" : 0.00
}, {
  "rank" : 207,
  "name" : "Complexity",
  "birthYear" : 2016,
  "color" : "鹿毛",
  "origin" : "",
  "runners" : 1,
  "winners" : 0,
  "starts" : 1,
  "wins" : 0,
  "prize" : 0,
  "prizePerStart" : 0,
  "prizePerHorse" : 0,
  "winRate" : 0.000,
  "earningIndex" : 0.00
}, {
  "rank" : 207,
  "name" : "Curlin",
  "birthYear" : 2004,
  "color" : "",
  "origin" : "米",
  "runners" : 1,
  "winners" : 0,
  "starts" : 1,
  "wins" : 0,
  "prize" : 0,
  "prizePerStart" : 0,
  "prizePerHorse" : 0,
  "winRate" : 0.000,
  "earningIndex" : 0.00
}, {
  "rank" : 207,
  "name" : "Dandy Man",
  "birthYear" : 2003,
  "color" : "",
  "origin" : "",
  "runners" : 2,
  "winners" : 0,
  "starts" : 2,
  "wins" : 0,
  "prize" : 0,
  "prizePerStart" : 0,
  "prizePerHorse" : 0,
  "winRate" : 0.000,
  "earningIndex" : 0.00
}, {
  "rank" : 207,
  "name" : "Daredevil",
  "birthYear" : 2012,
  "color" : "",
  "origin" : "",
  "runners" : 1,
  "winners" : 0,
  "starts" : 1,
  "wins" : 0,
  "prize" : 0,
  "prizePerStart" : 0,
  "prizePerHorse" : 0,
  "winRate" : 0.000,
  "earningIndex" : 0.00
}, {
  "rank" : 207,
  "name" : "Dawn Approach",
  "birthYear" : 2010,
  "color" : "",
  "origin" : "愛",
  "runners" : 1,
  "winners" : 0,
  "starts" : 1,
  "wins" : 0,
  "prize" : 0,
  "prizePerStart" : 0,
  "prizePerHorse" : 0,
  "winRate" : 0.000,
  "earningIndex" : 0.00
}, {
  "rank" : 207,
  "name" : "Earthlight",
  "birthYear" : 2017,
  "color" : "",
  "origin" : "",
  "runners" : 1,
  "winners" : 0,
  "starts" : 2,
  "wins" : 0,
  "prize" : 0,
  "prizePerStart" : 0,
  "prizePerHorse" : 0,
  "winRate" : 0.000,
  "earningIndex" : 0.00
}, {
  "rank" : 207,
  "name" : "Essential Quality",
  "birthYear" : 2018,
  "color" : "",
  "origin" : "",
  "runners" : 1,
  "winners" : 0,
  "starts" : 2,
  "wins" : 0,
  "prize" : 0,
  "prizePerStart" : 0,
  "prizePerHorse" : 0,
  "winRate" : 0.000,
  "earningIndex" : 0.00
}, {
  "rank" : 207,
  "name" : "Farhh",
  "birthYear" : 2008,
  "color" : "",
  "origin" : "英",
  "runners" : 1,
  "winners" : 0,
  "starts" : 1,
  "wins" : 0,
  "prize" : 0,
  "prizePerStart" : 0,
  "prizePerHorse" : 0,
  "winRate" : 0.000,
  "earningIndex" : 0.00
}, {
  "rank" : 207,
  "name" : "Global Campaign",
  "birthYear" : 2016,
  "color" : "鹿毛",
  "origin" : "",
  "runners" : 1,
  "winners" : 0,
  "starts" : 1,
  "wins" : 0,
  "prize" : 0,
  "prizePerStart" : 0,
  "prizePerHorse" : 0,
  "winRate" : 0.000,
  "earningIndex" : 0.00
}, {
  "rank" : 207,
  "name" : "Good Magic",
  "birthYear" : 2015,
  "color" : "",
  "origin" : "米",
  "runners" : 2,
  "winners" : 0,
  "starts" : 2,
  "wins" : 0,
  "prize" : 0,
  "prizePerStart" : 0,
  "prizePerHorse" : 0,
  "winRate" : 0.000,
  "earningIndex" : 0.00
}, {
  "rank" : 207,
  "name" : "Hard Spun",
  "birthYear" : 2004,
  "color" : "",
  "origin" : "米",
  "runners" : 1,
  "winners" : 0,
  "starts" : 1,
  "wins" : 0,
  "prize" : 0,
  "prizePerStart" : 0,
  "prizePerHorse" : 0,
  "winRate" : 0.000,
  "earningIndex" : 0.00
}, {
  "rank" : 207,
  "name" : "Hat Trick",
  "birthYear" : 2001,
  "color" : "",
  "origin" : "",
  "runners" : 1,
  "winners" : 0,
  "starts" : 1,
  "wins" : 0,
  "prize" : 0,
  "prizePerStart" : 0,
  "prizePerHorse" : 0,
  "winRate" : 0.000,
  "earningIndex" : 0.00
}, {
  "rank" : 207,
  "name" : "Iffraaj",
  "birthYear" : 2001,
  "color" : "",
  "origin" : "英",
  "runners" : 1,
  "winners" : 0,
  "starts" : 2,
  "wins" : 0,
  "prize" : 0,
  "prizePerStart" : 0,
  "prizePerHorse" : 0,
  "winRate" : 0.000,
  "earningIndex" : 0.00
}, {
  "rank" : 207,
  "name" : "Invincible Spirit",
  "birthYear" : 1997,
  "color" : "",
  "origin" : "愛",
  "runners" : 2,
  "winners" : 0,
  "starts" : 2,
  "wins" : 0,
  "prize" : 0,
  "prizePerStart" : 0,
  "prizePerHorse" : 0,
  "winRate" : 0.000,
  "earningIndex" : 0.00
}, {
  "rank" : 207,
  "name" : "Kitten's Joy",
  "birthYear" : 2001,
  "color" : "",
  "origin" : "米",
  "runners" : 1,
  "winners" : 0,
  "starts" : 1,
  "wins" : 0,
  "prize" : 0,
  "prizePerStart" : 0,
  "prizePerHorse" : 0,
  "winRate" : 0.000,
  "earningIndex" : 0.00
}, {
  "rank" : 207,
  "name" : "Knicks Go",
  "birthYear" : 2016,
  "color" : "",
  "origin" : "",
  "runners" : 1,
  "winners" : 0,
  "starts" : 1,
  "wins" : 0,
  "prize" : 0,
  "prizePerStart" : 0,
  "prizePerHorse" : 0,
  "winRate" : 0.000,
  "earningIndex" : 0.00
}, {
  "rank" : 207,
  "name" : "Known Agenda",
  "birthYear" : 2018,
  "color" : "栗毛",
  "origin" : "",
  "runners" : 1,
  "winners" : 0,
  "starts" : 1,
  "wins" : 0,
  "prize" : 0,
  "prizePerStart" : 0,
  "prizePerHorse" : 0,
  "winRate" : 0.000,
  "earningIndex" : 0.00
}, {
  "rank" : 207,
  "name" : "Lea",
  "birthYear" : 2009,
  "color" : "",
  "origin" : "",
  "runners" : 1,
  "winners" : 0,
  "starts" : 1,
  "wins" : 0,
  "prize" : 0,
  "prizePerStart" : 0,
  "prizePerHorse" : 0,
  "winRate" : 0.000,
  "earningIndex" : 0.00
}, {
  "rank" : 207,
  "name" : "Leinster",
  "birthYear" : 2015,
  "color" : "",
  "origin" : "",
  "runners" : 1,
  "winners" : 0,
  "starts" : 1,
  "wins" : 0,
  "prize" : 0,
  "prizePerStart" : 0,
  "prizePerHorse" : 0,
  "winRate" : 0.000,
  "earningIndex" : 0.00
}, {
  "rank" : 207,
  "name" : "Magna Grecia",
  "birthYear" : 2016,
  "color" : "",
  "origin" : "",
  "runners" : 1,
  "winners" : 0,
  "starts" : 1,
  "wins" : 0,
  "prize" : 0,
  "prizePerStart" : 0,
  "prizePerHorse" : 0,
  "winRate" : 0.000,
  "earningIndex" : 0.00
}, {
  "rank" : 207,
  "name" : "Masar",
  "birthYear" : 2015,
  "color" : "",
  "origin" : "",
  "runners" : 1,
  "winners" : 0,
  "starts" : 1,
  "wins" : 0,
  "prize" : 0,
  "prizePerStart" : 0,
  "prizePerHorse" : 0,
  "winRate" : 0.000,
  "earningIndex" : 0.00
}, {
  "rank" : 207,
  "name" : "Medaglia d'Oro",
  "birthYear" : 1999,
  "color" : "",
  "origin" : "米",
  "runners" : 1,
  "winners" : 0,
  "starts" : 1,
  "wins" : 0,
  "prize" : 0,
  "prizePerStart" : 0,
  "prizePerHorse" : 0,
  "winRate" : 0.000,
  "earningIndex" : 0.00
}, {
  "rank" : 207,
  "name" : "Not This Time",
  "birthYear" : 2014,
  "color" : "",
  "origin" : "",
  "runners" : 1,
  "winners" : 0,
  "starts" : 1,
  "wins" : 0,
  "prize" : 0,
  "prizePerStart" : 0,
  "prizePerHorse" : 0,
  "winRate" : 0.000,
  "earningIndex" : 0.00
}, {
  "rank" : 207,
  "name" : "Ocean Park",
  "birthYear" : 2008,
  "color" : "",
  "origin" : "",
  "runners" : 1,
  "winners" : 0,
  "starts" : 1,
  "wins" : 0,
  "prize" : 0,
  "prizePerStart" : 0,
  "prizePerHorse" : 0,
  "winRate" : 0.000,
  "earningIndex" : 0.00
}, {
  "rank" : 207,
  "name" : "Palace Malice",
  "birthYear" : 2010,
  "color" : "",
  "origin" : "米",
  "runners" : 1,
  "winners" : 0,
  "starts" : 1,
  "wins" : 0,
  "prize" : 0,
  "prizePerStart" : 0,
  "prizePerHorse" : 0,
  "winRate" : 0.000,
  "earningIndex" : 0.00
}, {
  "rank" : 207,
  "name" : "Palace Pier",
  "birthYear" : 2017,
  "color" : "",
  "origin" : "",
  "runners" : 2,
  "winners" : 0,
  "starts" : 3,
  "wins" : 0,
  "prize" : 0,
  "prizePerStart" : 0,
  "prizePerHorse" : 0,
  "winRate" : 0.000,
  "earningIndex" : 0.00
}, {
  "rank" : 207,
  "name" : "Runhappy",
  "birthYear" : 2012,
  "color" : "",
  "origin" : "",
  "runners" : 1,
  "winners" : 0,
  "starts" : 1,
  "wins" : 0,
  "prize" : 0,
  "prizePerStart" : 0,
  "prizePerHorse" : 0,
  "winRate" : 0.000,
  "earningIndex" : 0.00
}, {
  "rank" : 207,
  "name" : "Sottsass",
  "birthYear" : 2016,
  "color" : "",
  "origin" : "",
  "runners" : 2,
  "winners" : 0,
  "starts" : 2,
  "wins" : 0,
  "prize" : 0,
  "prizePerStart" : 0,
  "prizePerHorse" : 0,
  "winRate" : 0.000,
  "earningIndex" : 0.00
}, {
  "rank" : 207,
  "name" : "St Patrick's Day",
  "birthYear" : 2015,
  "color" : "",
  "origin" : "",
  "runners" : 1,
  "winners" : 0,
  "starts" : 2,
  "wins" : 0,
  "prize" : 0,
  "prizePerStart" : 0,
  "prizePerHorse" : 0,
  "winRate" : 0.000,
  "earningIndex" : 0.00
}, {
  "rank" : 207,
  "name" : "Tom's d'Etat",
  "birthYear" : 2013,
  "color" : "",
  "origin" : "",
  "runners" : 1,
  "winners" : 0,
  "starts" : 1,
  "wins" : 0,
  "prize" : 0,
  "prizePerStart" : 0,
  "prizePerHorse" : 0,
  "winRate" : 0.000,
  "earningIndex" : 0.00
}, {
  "rank" : 207,
  "name" : "Twirling Candy",
  "birthYear" : 2007,
  "color" : "",
  "origin" : "",
  "runners" : 1,
  "winners" : 0,
  "starts" : 1,
  "wins" : 0,
  "prize" : 0,
  "prizePerStart" : 0,
  "prizePerHorse" : 0,
  "winRate" : 0.000,
  "earningIndex" : 0.00
}, {
  "rank" : 207,
  "name" : "Uncle Mo",
  "birthYear" : 2008,
  "color" : "",
  "origin" : "米",
  "runners" : 1,
  "winners" : 0,
  "starts" : 1,
  "wins" : 0,
  "prize" : 0,
  "prizePerStart" : 0,
  "prizePerHorse" : 0,
  "winRate" : 0.000,
  "earningIndex" : 0.00
}, {
  "rank" : 207,
  "name" : "Vekoma",
  "birthYear" : 2016,
  "color" : "",
  "origin" : "",
  "runners" : 2,
  "winners" : 0,
  "starts" : 2,
  "wins" : 0,
  "prize" : 0,
  "prizePerStart" : 0,
  "prizePerHorse" : 0,
  "winRate" : 0.000,
  "earningIndex" : 0.00
}, {
  "rank" : 207,
  "name" : "War Front",
  "birthYear" : 2002,
  "color" : "",
  "origin" : "米",
  "runners" : 1,
  "winners" : 0,
  "starts" : 1,
  "wins" : 0,
  "prize" : 0,
  "prizePerStart" : 0,
  "prizePerHorse" : 0,
  "winRate" : 0.000,
  "earningIndex" : 0.00
}, {
  "rank" : 207,
  "name" : "Written Tycoon",
  "birthYear" : 2002,
  "color" : "",
  "origin" : "",
  "runners" : 1,
  "winners" : 0,
  "starts" : 1,
  "wins" : 0,
  "prize" : 0,
  "prizePerStart" : 0,
  "prizePerHorse" : 0,
  "winRate" : 0.000,
  "earningIndex" : 0.00
}, {
  "rank" : 207,
  "name" : "Yaupon",
  "birthYear" : 2017,
  "color" : "鹿毛",
  "origin" : "米",
  "runners" : 2,
  "winners" : 0,
  "starts" : 3,
  "wins" : 0,
  "prize" : 0,
  "prizePerStart" : 0,
  "prizePerHorse" : 0,
  "winRate" : 0.000,
  "earningIndex" : 0.00
}, {
  "rank" : 207,
  "name" : "Zarak",
  "birthYear" : 2013,
  "color" : "",
  "origin" : "",
  "runners" : 1,
  "winners" : 0,
  "starts" : 2,
  "wins" : 0,
  "prize" : 0,
  "prizePerStart" : 0,
  "prizePerHorse" : 0,
  "winRate" : 0.000,
  "earningIndex" : 0.00
}, {
  "rank" : 207,
  "name" : "アイルハヴアナザー",
  "birthYear" : 2009,
  "color" : "栗毛",
  "origin" : "米",
  "runners" : 1,
  "winners" : 0,
  "starts" : 1,
  "wins" : 0,
  "prize" : 0,
  "prizePerStart" : 0,
  "prizePerHorse" : 0,
  "winRate" : 0.000,
  "earningIndex" : 0.00
}, {
  "rank" : 207,
  "name" : "アスクピーターパン",
  "birthYear" : 2018,
  "color" : "鹿毛",
  "origin" : "英",
  "runners" : 4,
  "winners" : 0,
  "starts" : 4,
  "wins" : 0,
  "prize" : 0,
  "prizePerStart" : 0,
  "prizePerHorse" : 0,
  "winRate" : 0.000,
  "earningIndex" : 0.00
}, {
  "rank" : 207,
  "name" : "アロマカフェ",
  "birthYear" : 2007,
  "color" : "黒鹿毛",
  "origin" : "新冠町",
  "runners" : 1,
  "winners" : 0,
  "starts" : 1,
  "wins" : 0,
  "prize" : 0,
  "prizePerStart" : 0,
  "prizePerHorse" : 0,
  "winRate" : 0.000,
  "earningIndex" : 0.00
}, {
  "rank" : 207,
  "name" : "ウインバリアシオン",
  "birthYear" : 2008,
  "color" : "鹿毛",
  "origin" : "安平町",
  "runners" : 2,
  "winners" : 0,
  "starts" : 2,
  "wins" : 0,
  "prize" : 0,
  "prizePerStart" : 0,
  "prizePerHorse" : 0,
  "winRate" : 0.000,
  "earningIndex" : 0.00
}, {
  "rank" : 207,
  "name" : "エーシントップ",
  "birthYear" : 2010,
  "color" : "黒鹿毛",
  "origin" : "米",
  "runners" : 2,
  "winners" : 0,
  "starts" : 2,
  "wins" : 0,
  "prize" : 0,
  "prizePerStart" : 0,
  "prizePerHorse" : 0,
  "winRate" : 0.000,
  "earningIndex" : 0.00
}, {
  "rank" : 207,
  "name" : "エタリオウ",
  "birthYear" : 2015,
  "color" : "青鹿毛",
  "origin" : "安平町",
  "runners" : 1,
  "winners" : 0,
  "starts" : 1,
  "wins" : 0,
  "prize" : 0,
  "prizePerStart" : 0,
  "prizePerHorse" : 0,
  "winRate" : 0.000,
  "earningIndex" : 0.00
}, {
  "rank" : 207,
  "name" : "エピカリス",
  "birthYear" : 2014,
  "color" : "黒鹿毛",
  "origin" : "浦河町",
  "runners" : 3,
  "winners" : 0,
  "starts" : 3,
  "wins" : 0,
  "prize" : 0,
  "prizePerStart" : 0,
  "prizePerHorse" : 0,
  "winRate" : 0.000,
  "earningIndex" : 0.00
}, {
  "rank" : 207,
  "name" : "エンパイアペガサス",
  "birthYear" : 2013,
  "color" : "鹿毛",
  "origin" : "新冠町",
  "runners" : 1,
  "winners" : 0,
  "starts" : 1,
  "wins" : 0,
  "prize" : 0,
  "prizePerStart" : 0,
  "prizePerHorse" : 0,
  "winRate" : 0.000,
  "earningIndex" : 0.00
}, {
  "rank" : 207,
  "name" : "オーヴァルエース",
  "birthYear" : 2016,
  "color" : "栗毛",
  "origin" : "浦河町",
  "runners" : 2,
  "winners" : 0,
  "starts" : 2,
  "wins" : 0,
  "prize" : 0,
  "prizePerStart" : 0,
  "prizePerHorse" : 0,
  "winRate" : 0.000,
  "earningIndex" : 0.00
}, {
  "rank" : 207,
  "name" : "オンファイア",
  "birthYear" : 2003,
  "color" : "鹿毛",
  "origin" : "早来町",
  "runners" : 1,
  "winners" : 0,
  "starts" : 2,
  "wins" : 0,
  "prize" : 0,
  "prizePerStart" : 0,
  "prizePerHorse" : 0,
  "winRate" : 0.000,
  "earningIndex" : 0.00
}, {
  "rank" : 207,
  "name" : "カジノドライヴ",
  "birthYear" : 2005,
  "color" : "栗毛",
  "origin" : "米",
  "runners" : 1,
  "winners" : 0,
  "starts" : 1,
  "wins" : 0,
  "prize" : 0,
  "prizePerStart" : 0,
  "prizePerHorse" : 0,
  "winRate" : 0.000,
  "earningIndex" : 0.00
}, {
  "rank" : 207,
  "name" : "ガルボ",
  "birthYear" : 2007,
  "color" : "青毛",
  "origin" : "様似町",
  "runners" : 3,
  "winners" : 0,
  "starts" : 3,
  "wins" : 0,
  "prize" : 0,
  "prizePerStart" : 0,
  "prizePerHorse" : 0,
  "winRate" : 0.000,
  "earningIndex" : 0.00
}, {
  "rank" : 207,
  "name" : "キャプテンキング",
  "birthYear" : 2014,
  "color" : "鹿毛",
  "origin" : "新ひだか町",
  "runners" : 1,
  "winners" : 0,
  "starts" : 1,
  "wins" : 0,
  "prize" : 0,
  "prizePerStart" : 0,
  "prizePerHorse" : 0,
  "winRate" : 0.000,
  "earningIndex" : 0.00
}, {
  "rank" : 207,
  "name" : "キングヘイロー",
  "birthYear" : 1995,
  "color" : "鹿毛",
  "origin" : "新冠町",
  "runners" : 1,
  "winners" : 0,
  "starts" : 1,
  "wins" : 0,
  "prize" : 0,
  "prizePerStart" : 0,
  "prizePerHorse" : 0,
  "winRate" : 0.000,
  "earningIndex" : 0.00
}, {
  "rank" : 207,
  "name" : "クリエイター2",
  "birthYear" : 2013,
  "color" : "芦毛",
  "origin" : "米",
  "runners" : 1,
  "winners" : 0,
  "starts" : 2,
  "wins" : 0,
  "prize" : 0,
  "prizePerStart" : 0,
  "prizePerHorse" : 0,
  "winRate" : 0.000,
  "earningIndex" : 0.00
}, {
  "rank" : 207,
  "name" : "グランプリボス",
  "birthYear" : 2008,
  "color" : "鹿毛",
  "origin" : "安平町",
  "runners" : 2,
  "winners" : 0,
  "starts" : 2,
  "wins" : 0,
  "prize" : 0,
  "prizePerStart" : 0,
  "prizePerHorse" : 0,
  "winRate" : 0.000,
  "earningIndex" : 0.00
}, {
  "rank" : 207,
  "name" : "コパノリチャード",
  "birthYear" : 2010,
  "color" : "黒鹿毛",
  "origin" : "日高町",
  "runners" : 1,
  "winners" : 0,
  "starts" : 1,
  "wins" : 0,
  "prize" : 0,
  "prizePerStart" : 0,
  "prizePerHorse" : 0,
  "winRate" : 0.000,
  "earningIndex" : 0.00
}, {
  "rank" : 207,
  "name" : "ゴールドアリュール",
  "birthYear" : 1999,
  "color" : "栗毛",
  "origin" : "追分町",
  "runners" : 1,
  "winners" : 0,
  "starts" : 2,
  "wins" : 0,
  "prize" : 0,
  "prizePerStart" : 0,
  "prizePerHorse" : 0,
  "winRate" : 0.000,
  "earningIndex" : 0.00
}, {
  "rank" : 207,
  "name" : "サトノインプレッサ",
  "birthYear" : 2017,
  "color" : "黒鹿毛",
  "origin" : "千歳市",
  "runners" : 2,
  "winners" : 0,
  "starts" : 5,
  "wins" : 0,
  "prize" : 0,
  "prizePerStart" : 0,
  "prizePerHorse" : 0,
  "winRate" : 0.000,
  "earningIndex" : 0.00
}, {
  "rank" : 207,
  "name" : "サンライズソア",
  "birthYear" : 2014,
  "color" : "青鹿毛",
  "origin" : "浦河町",
  "runners" : 2,
  "winners" : 0,
  "starts" : 2,
  "wins" : 0,
  "prize" : 0,
  "prizePerStart" : 0,
  "prizePerHorse" : 0,
  "winRate" : 0.000,
  "earningIndex" : 0.00
}, {
  "rank" : 207,
  "name" : "ザファクター",
  "birthYear" : 2008,
  "color" : "芦毛",
  "origin" : "米",
  "runners" : 1,
  "winners" : 0,
  "starts" : 1,
  "wins" : 0,
  "prize" : 0,
  "prizePerStart" : 0,
  "prizePerHorse" : 0,
  "winRate" : 0.000,
  "earningIndex" : 0.00
}, {
  "rank" : 207,
  "name" : "シュウジ",
  "birthYear" : 2013,
  "color" : "鹿毛",
  "origin" : "日高町",
  "runners" : 1,
  "winners" : 0,
  "starts" : 1,
  "wins" : 0,
  "prize" : 0,
  "prizePerStart" : 0,
  "prizePerHorse" : 0,
  "winRate" : 0.000,
  "earningIndex" : 0.00
}, {
  "rank" : 207,
  "name" : "ショウナンバッハ",
  "birthYear" : 2011,
  "color" : "鹿毛",
  "origin" : "日高町",
  "runners" : 1,
  "winners" : 0,
  "starts" : 1,
  "wins" : 0,
  "prize" : 0,
  "prizePerStart" : 0,
  "prizePerHorse" : 0,
  "winRate" : 0.000,
  "earningIndex" : 0.00
}, {
  "rank" : 207,
  "name" : "ジャングルポケット",
  "birthYear" : 1998,
  "color" : "鹿毛",
  "origin" : "早来町",
  "runners" : 1,
  "winners" : 0,
  "starts" : 1,
  "wins" : 0,
  "prize" : 0,
  "prizePerStart" : 0,
  "prizePerHorse" : 0,
  "winRate" : 0.000,
  "earningIndex" : 0.00
}, {
  "rank" : 207,
  "name" : "ストーミーシー",
  "birthYear" : 2013,
  "color" : "栗毛",
  "origin" : "浦河町",
  "runners" : 3,
  "winners" : 0,
  "starts" : 5,
  "wins" : 0,
  "prize" : 0,
  "prizePerStart" : 0,
  "prizePerHorse" : 0,
  "winRate" : 0.000,
  "earningIndex" : 0.00
}, {
  "rank" : 207,
  "name" : "スピリッツミノル",
  "birthYear" : 2012,
  "color" : "栗毛",
  "origin" : "新ひだか町",
  "runners" : 1,
  "winners" : 0,
  "starts" : 1,
  "wins" : 0,
  "prize" : 0,
  "prizePerStart" : 0,
  "prizePerHorse" : 0,
  "winRate" : 0.000,
  "earningIndex" : 0.00
}, {
  "rank" : 207,
  "name" : "スマートオーディン",
  "birthYear" : 2013,
  "color" : "黒鹿毛",
  "origin" : "新冠町",
  "runners" : 3,
  "winners" : 0,
  "starts" : 3,
  "wins" : 0,
  "prize" : 0,
  "prizePerStart" : 0,
  "prizePerHorse" : 0,
  "winRate" : 0.000,
  "earningIndex" : 0.00
}, {
  "rank" : 207,
  "name" : "セイウンコウセイ",
  "birthYear" : 2013,
  "color" : "栗毛",
  "origin" : "新ひだか町",
  "runners" : 7,
  "winners" : 0,
  "starts" : 7,
  "wins" : 0,
  "prize" : 0,
  "prizePerStart" : 0,
  "prizePerHorse" : 0,
  "winRate" : 0.000,
  "earningIndex" : 0.00
}, {
  "rank" : 207,
  "name" : "ゼンノロブロイ",
  "birthYear" : 2000,
  "color" : "黒鹿毛",
  "origin" : "白老町",
  "runners" : 1,
  "winners" : 0,
  "starts" : 2,
  "wins" : 0,
  "prize" : 0,
  "prizePerStart" : 0,
  "prizePerHorse" : 0,
  "winRate" : 0.000,
  "earningIndex" : 0.00
}, {
  "rank" : 207,
  "name" : "タイセイレジェンド",
  "birthYear" : 2007,
  "color" : "栗毛",
  "origin" : "安平町",
  "runners" : 2,
  "winners" : 0,
  "starts" : 2,
  "wins" : 0,
  "prize" : 0,
  "prizePerStart" : 0,
  "prizePerHorse" : 0,
  "winRate" : 0.000,
  "earningIndex" : 0.00
}, {
  "rank" : 207,
  "name" : "タツゴウゲキ",
  "birthYear" : 2012,
  "color" : "鹿毛",
  "origin" : "新冠町",
  "runners" : 1,
  "winners" : 0,
  "starts" : 1,
  "wins" : 0,
  "prize" : 0,
  "prizePerStart" : 0,
  "prizePerHorse" : 0,
  "winRate" : 0.000,
  "earningIndex" : 0.00
}, {
  "rank" : 207,
  "name" : "タニノフランケル",
  "birthYear" : 2015,
  "color" : "青鹿毛",
  "origin" : "愛",
  "runners" : 11,
  "winners" : 0,
  "starts" : 12,
  "wins" : 0,
  "prize" : 0,
  "prizePerStart" : 0,
  "prizePerHorse" : 0,
  "winRate" : 0.000,
  "earningIndex" : 0.00
}, {
  "rank" : 207,
  "name" : "ダノンシャンティ",
  "birthYear" : 2007,
  "color" : "黒鹿毛",
  "origin" : "日高町",
  "runners" : 1,
  "winners" : 0,
  "starts" : 2,
  "wins" : 0,
  "prize" : 0,
  "prizePerStart" : 0,
  "prizePerHorse" : 0,
  "winRate" : 0.000,
  "earningIndex" : 0.00
}, {
  "rank" : 207,
  "name" : "ディープスカイ",
  "birthYear" : 2005,
  "color" : "栗毛",
  "origin" : "浦河町",
  "runners" : 1,
  "winners" : 0,
  "starts" : 1,
  "wins" : 0,
  "prize" : 0,
  "prizePerStart" : 0,
  "prizePerHorse" : 0,
  "winRate" : 0.000,
  "earningIndex" : 0.00
}, {
  "rank" : 207,
  "name" : "トーセンジョーダン",
  "birthYear" : 2006,
  "color" : "鹿毛",
  "origin" : "早来町",
  "runners" : 1,
  "winners" : 0,
  "starts" : 1,
  "wins" : 0,
  "prize" : 0,
  "prizePerStart" : 0,
  "prizePerHorse" : 0,
  "winRate" : 0.000,
  "earningIndex" : 0.00
}, {
  "rank" : 207,
  "name" : "トーセンホマレボシ",
  "birthYear" : 2009,
  "color" : "鹿毛",
  "origin" : "安平町",
  "runners" : 1,
  "winners" : 0,
  "starts" : 1,
  "wins" : 0,
  "prize" : 0,
  "prizePerStart" : 0,
  "prizePerHorse" : 0,
  "winRate" : 0.000,
  "earningIndex" : 0.00
}, {
  "rank" : 207,
  "name" : "トーセンレーヴ",
  "birthYear" : 2008,
  "color" : "鹿毛",
  "origin" : "安平町",
  "runners" : 2,
  "winners" : 0,
  "starts" : 2,
  "wins" : 0,
  "prize" : 0,
  "prizePerStart" : 0,
  "prizePerHorse" : 0,
  "winRate" : 0.000,
  "earningIndex" : 0.00
}, {
  "rank" : 207,
  "name" : "トゥザグローリー",
  "birthYear" : 2007,
  "color" : "鹿毛",
  "origin" : "安平町",
  "runners" : 4,
  "winners" : 0,
  "starts" : 4,
  "wins" : 0,
  "prize" : 0,
  "prizePerStart" : 0,
  "prizePerHorse" : 0,
  "winRate" : 0.000,
  "earningIndex" : 0.00
}, {
  "rank" : 207,
  "name" : "トウケイヘイロー",
  "birthYear" : 2009,
  "color" : "鹿毛",
  "origin" : "浦河町",
  "runners" : 1,
  "winners" : 0,
  "starts" : 1,
  "wins" : 0,
  "prize" : 0,
  "prizePerStart" : 0,
  "prizePerHorse" : 0,
  "winRate" : 0.000,
  "earningIndex" : 0.00
}, {
  "rank" : 207,
  "name" : "トビーズコーナー",
  "birthYear" : 2008,
  "color" : "栗毛",
  "origin" : "米",
  "runners" : 4,
  "winners" : 0,
  "starts" : 4,
  "wins" : 0,
  "prize" : 0,
  "prizePerStart" : 0,
  "prizePerHorse" : 0,
  "winRate" : 0.000,
  "earningIndex" : 0.00
}, {
  "rank" : 207,
  "name" : "ナカヤマフェスタ",
  "birthYear" : 2006,
  "color" : "鹿毛",
  "origin" : "むかわ町",
  "runners" : 1,
  "winners" : 0,
  "starts" : 1,
  "wins" : 0,
  "prize" : 0,
  "prizePerStart" : 0,
  "prizePerHorse" : 0,
  "winRate" : 0.000,
  "earningIndex" : 0.00
}, {
  "rank" : 207,
  "name" : "ニシケンモノノフ",
  "birthYear" : 2011,
  "color" : "栗毛",
  "origin" : "新冠町",
  "runners" : 1,
  "winners" : 0,
  "starts" : 2,
  "wins" : 0,
  "prize" : 0,
  "prizePerStart" : 0,
  "prizePerHorse" : 0,
  "winRate" : 0.000,
  "earningIndex" : 0.00
}, {
  "rank" : 207,
  "name" : "ニホンピロアワーズ",
  "birthYear" : 2007,
  "color" : "青鹿毛",
  "origin" : "新ひだか町",
  "runners" : 1,
  "winners" : 0,
  "starts" : 2,
  "wins" : 0,
  "prize" : 0,
  "prizePerStart" : 0,
  "prizePerHorse" : 0,
  "winRate" : 0.000,
  "earningIndex" : 0.00
}, {
  "rank" : 207,
  "name" : "ハギノハイブリッド",
  "birthYear" : 2011,
  "color" : "栗毛",
  "origin" : "千歳市",
  "runners" : 1,
  "winners" : 0,
  "starts" : 2,
  "wins" : 0,
  "prize" : 0,
  "prizePerStart" : 0,
  "prizePerHorse" : 0,
  "winRate" : 0.000,
  "earningIndex" : 0.00
}, {
  "rank" : 207,
  "name" : "ハッピースプリント",
  "birthYear" : 2011,
  "color" : "鹿毛",
  "origin" : "浦河町",
  "runners" : 2,
  "winners" : 0,
  "starts" : 4,
  "wins" : 0,
  "prize" : 0,
  "prizePerStart" : 0,
  "prizePerHorse" : 0,
  "winRate" : 0.000,
  "earningIndex" : 0.00
}, {
  "rank" : 207,
  "name" : "パドトロワ",
  "birthYear" : 2007,
  "color" : "鹿毛",
  "origin" : "千歳市",
  "runners" : 4,
  "winners" : 0,
  "starts" : 5,
  "wins" : 0,
  "prize" : 0,
  "prizePerStart" : 0,
  "prizePerHorse" : 0,
  "winRate" : 0.000,
  "earningIndex" : 0.00
}, {
  "rank" : 207,
  "name" : "フリオーソ",
  "birthYear" : 2004,
  "color" : "栗毛",
  "origin" : "新冠町",
  "runners" : 3,
  "winners" : 0,
  "starts" : 3,
  "wins" : 0,
  "prize" : 0,
  "prizePerStart" : 0,
  "prizePerHorse" : 0,
  "winRate" : 0.000,
  "earningIndex" : 0.00
}, {
  "rank" : 207,
  "name" : "プリサイスエンド",
  "birthYear" : 1997,
  "color" : "黒鹿毛",
  "origin" : "米",
  "runners" : 2,
  "winners" : 0,
  "starts" : 3,
  "wins" : 0,
  "prize" : 0,
  "prizePerStart" : 0,
  "prizePerHorse" : 0,
  "winRate" : 0.000,
  "earningIndex" : 0.00
}, {
  "rank" : 207,
  "name" : "ベーカバド",
  "birthYear" : 2007,
  "color" : "鹿毛",
  "origin" : "仏",
  "runners" : 2,
  "winners" : 0,
  "starts" : 2,
  "wins" : 0,
  "prize" : 0,
  "prizePerStart" : 0,
  "prizePerHorse" : 0,
  "winRate" : 0.000,
  "earningIndex" : 0.00
}, {
  "rank" : 207,
  "name" : "マツリダゴッホ",
  "birthYear" : 2003,
  "color" : "鹿毛",
  "origin" : "静内町",
  "runners" : 1,
  "winners" : 0,
  "starts" : 1,
  "wins" : 0,
  "prize" : 0,
  "prizePerStart" : 0,
  "prizePerHorse" : 0,
  "winRate" : 0.000,
  "earningIndex" : 0.00
}, {
  "rank" : 207,
  "name" : "ミッキースワロー",
  "birthYear" : 2014,
  "color" : "鹿毛",
  "origin" : "安平町",
  "runners" : 1,
  "winners" : 0,
  "starts" : 2,
  "wins" : 0,
  "prize" : 0,
  "prizePerStart" : 0,
  "prizePerHorse" : 0,
  "winRate" : 0.000,
  "earningIndex" : 0.00
}, {
  "rank" : 207,
  "name" : "ミュゼスルタン",
  "birthYear" : 2012,
  "color" : "鹿毛",
  "origin" : "千歳市",
  "runners" : 1,
  "winners" : 0,
  "starts" : 2,
  "wins" : 0,
  "prize" : 0,
  "prizePerStart" : 0,
  "prizePerHorse" : 0,
  "winRate" : 0.000,
  "earningIndex" : 0.00
}, {
  "rank" : 207,
  "name" : "メイショウボーラー",
  "birthYear" : 2001,
  "color" : "黒鹿毛",
  "origin" : "浦河町",
  "runners" : 3,
  "winners" : 0,
  "starts" : 3,
  "wins" : 0,
  "prize" : 0,
  "prizePerStart" : 0,
  "prizePerHorse" : 0,
  "winRate" : 0.000,
  "earningIndex" : 0.00
}, {
  "rank" : 207,
  "name" : "ヤングマンパワー",
  "birthYear" : 2012,
  "color" : "黒鹿毛",
  "origin" : "安平町",
  "runners" : 1,
  "winners" : 0,
  "starts" : 1,
  "wins" : 0,
  "prize" : 0,
  "prizePerStart" : 0,
  "prizePerHorse" : 0,
  "winRate" : 0.000,
  "earningIndex" : 0.00
}, {
  "rank" : 207,
  "name" : "レーヴミストラル",
  "birthYear" : 2012,
  "color" : "鹿毛",
  "origin" : "安平町",
  "runners" : 2,
  "winners" : 0,
  "starts" : 2,
  "wins" : 0,
  "prize" : 0,
  "prizePerStart" : 0,
  "prizePerHorse" : 0,
  "winRate" : 0.000,
  "earningIndex" : 0.00
}, {
  "rank" : 207,
  "name" : "レッドスパーダ",
  "birthYear" : 2006,
  "color" : "鹿毛",
  "origin" : "日高町",
  "runners" : 2,
  "winners" : 0,
  "starts" : 2,
  "wins" : 0,
  "prize" : 0,
  "prizePerStart" : 0,
  "prizePerHorse" : 0,
  "winRate" : 0.000,
  "earningIndex" : 0.00
}, {
  "rank" : 207,
  "name" : "ローエングリン",
  "birthYear" : 1999,
  "color" : "栗毛",
  "origin" : "千歳市",
  "runners" : 1,
  "winners" : 0,
  "starts" : 1,
  "wins" : 0,
  "prize" : 0,
  "prizePerStart" : 0,
  "prizePerHorse" : 0,
  "winRate" : 0.000,
  "earningIndex" : 0.00
}, {
  "rank" : 207,
  "name" : "ロンドンタウン",
  "birthYear" : 2013,
  "color" : "鹿毛",
  "origin" : "新冠町",
  "runners" : 1,
  "winners" : 0,
  "starts" : 2,
  "wins" : 0,
  "prize" : 0,
  "prizePerStart" : 0,
  "prizePerHorse" : 0,
  "winRate" : 0.000,
  "earningIndex" : 0.00
}, {
  "rank" : 207,
  "name" : "ワンアンドオンリー",
  "birthYear" : 2011,
  "color" : "黒鹿毛",
  "origin" : "新冠町",
  "runners" : 1,
  "winners" : 0,
  "starts" : 1,
  "wins" : 0,
  "prize" : 0,
  "prizePerStart" : 0,
  "prizePerHorse" : 0,
  "winRate" : 0.000,
  "earningIndex" : 0.00
}, {
  "rank" : 207,
  "name" : "ワンダーアキュート",
  "birthYear" : 2006,
  "color" : "鹿毛",
  "origin" : "三石町",
  "runners" : 1,
  "winners" : 0,
  "starts" : 1,
  "wins" : 0,
  "prize" : 0,
  "prizePerStart" : 0,
  "prizePerHorse" : 0,
  "winRate" : 0.000,
  "earningIndex" : 0.00
} ]